[{"t":0,"event":"Position","px":258,"py":706,"x":-143.32,"z":-193.39,"is_bot":false},{"t":21,"event":"Position","px":247,"py":700,"x":-152.66,"z":-188.6,"is_bot":false},{"t":26,"event":"Position","px":251,"py":696,"x":-149.14,"z":-185.04,"is_bot":false},{"t":31,"event":"Position","px":243,"py":689,"x":-156.27,"z":-178.83,"is_bot":false},{"t":36,"event":"Position","px":225,"py":706,"x":-172.01,"z":-193.32,"is_bot":false},{"t":38,"event":"Loot","px":225,"py":706,"x":-172.47,"z":-193.12,"is_bot":false},{"t":41,"event":"Position","px":225,"py":716,"x":-171.99,"z":-202.18,"is_bot":false},{"t":46,"event":"Position","px":235,"py":750,"x":-163.5,"z":-232.08,"is_bot":false},{"t":51,"event":"Position","px":239,"py":766,"x":-160.0,"z":-246.6,"is_bot":false},{"t":56,"event":"Position","px":234,"py":768,"x":-164.14,"z":-247.97,"is_bot":false},{"t":66,"event":"Position","px":231,"py":767,"x":-167.13,"z":-246.78,"is_bot":false},{"t":86,"event":"Position","px":227,"py":763,"x":-170.21,"z":-243.28,"is_bot":false},{"t":91,"event":"Position","px":233,"py":764,"x":-164.85,"z":-244.29,"is_bot":false},{"t":95,"event":"BotKill","px":241,"py":760,"x":-158.54,"z":-240.72,"is_bot":false},{"t":96,"event":"Position","px":241,"py":760,"x":-158.54,"z":-240.72,"is_bot":false},{"t":101,"event":"Position","px":241,"py":747,"x":-158.62,"z":-229.95,"is_bot":false},{"t":106,"event":"Position","px":247,"py":729,"x":-153.11,"z":-213.36,"is_bot":false},{"t":106,"event":"Loot","px":247,"py":729,"x":-153.11,"z":-213.36,"is_bot":false},{"t":111,"event":"Position","px":253,"py":712,"x":-147.32,"z":-198.92,"is_bot":false},{"t":116,"event":"Position","px":280,"py":704,"x":-124.07,"z":-191.67,"is_bot":false},{"t":121,"event":"Position","px":304,"py":706,"x":-102.89,"z":-193.51,"is_bot":false},{"t":126,"event":"Position","px":327,"py":681,"x":-83.02,"z":-171.82,"is_bot":false},{"t":131,"event":"Position","px":336,"py":664,"x":-75.09,"z":-156.39,"is_bot":false},{"t":131,"event":"Loot","px":336,"py":664,"x":-75.09,"z":-156.39,"is_bot":false},{"t":132,"event":"Loot","px":336,"py":664,"x":-75.09,"z":-156.39,"is_bot":false},{"t":136,"event":"Position","px":328,"py":662,"x":-81.49,"z":-154.63,"is_bot":false},{"t":141,"event":"Position","px":356,"py":645,"x":-56.89,"z":-139.55,"is_bot":false},{"t":146,"event":"Position","px":367,"py":613,"x":-47.65,"z":-111.54,"is_bot":false},{"t":151,"event":"Position","px":363,"py":580,"x":-51.26,"z":-83.1,"is_bot":false},{"t":156,"event":"Position","px":346,"py":566,"x":-65.58,"z":-70.86,"is_bot":false},{"t":161,"event":"Position","px":336,"py":563,"x":-74.39,"z":-67.52,"is_bot":false},{"t":165,"event":"Loot","px":333,"py":556,"x":-77.1,"z":-61.76,"is_bot":false},{"t":166,"event":"Position","px":336,"py":557,"x":-74.83,"z":-62.29,"is_bot":false},{"t":167,"event":"Loot","px":336,"py":557,"x":-74.83,"z":-62.29,"is_bot":false},{"t":176,"event":"Position","px":341,"py":566,"x":-70.38,"z":-70.06,"is_bot":false},{"t":181,"event":"Position","px":346,"py":564,"x":-65.65,"z":-69.12,"is_bot":false},{"t":192,"event":"Position","px":332,"py":560,"x":-78.35,"z":-64.93,"is_bot":false},{"t":197,"event":"Position","px":340,"py":559,"x":-70.77,"z":-63.98,"is_bot":false},{"t":200,"event":"BotKill","px":347,"py":565,"x":-64.62,"z":-69.29,"is_bot":false},{"t":202,"event":"Position","px":348,"py":564,"x":-64.01,"z":-69.07,"is_bot":false},{"t":207,"event":"Position","px":358,"py":570,"x":-55.26,"z":-74.41,"is_bot":false},{"t":211,"event":"Loot","px":367,"py":576,"x":-47.13,"z":-79.23,"is_bot":false},{"t":211,"event":"Loot","px":367,"py":576,"x":-47.13,"z":-79.23,"is_bot":false},{"t":212,"event":"Position","px":367,"py":576,"x":-47.35,"z":-79.35,"is_bot":false},{"t":217,"event":"Position","px":345,"py":577,"x":-67.15,"z":-80.25,"is_bot":false},{"t":222,"event":"Position","px":328,"py":561,"x":-82.15,"z":-65.81,"is_bot":false},{"t":227,"event":"Position","px":325,"py":544,"x":-84.42,"z":-50.96,"is_bot":false},{"t":232,"event":"Position","px":331,"py":546,"x":-79.48,"z":-53.14,"is_bot":false},{"t":237,"event":"Position","px":324,"py":554,"x":-85.5,"z":-59.55,"is_bot":false},{"t":242,"event":"Position","px":328,"py":568,"x":-81.39,"z":-72.45,"is_bot":false},{"t":247,"event":"Position","px":354,"py":571,"x":-59.15,"z":-74.79,"is_bot":false},{"t":252,"event":"Position","px":369,"py":552,"x":-46.12,"z":-58.11,"is_bot":false},{"t":257,"event":"Position","px":370,"py":540,"x":-44.41,"z":-47.7,"is_bot":false},{"t":262,"event":"Position","px":378,"py":547,"x":-38.2,"z":-54.02,"is_bot":false},{"t":266,"event":"BotKill","px":385,"py":544,"x":-31.84,"z":-51.11,"is_bot":false},{"t":267,"event":"Position","px":385,"py":545,"x":-31.72,"z":-51.73,"is_bot":false},{"t":267,"event":"Loot","px":385,"py":545,"x":-31.98,"z":-51.68,"is_bot":false},{"t":272,"event":"Position","px":367,"py":533,"x":-47.16,"z":-41.87,"is_bot":false},{"t":277,"event":"Position","px":333,"py":543,"x":-76.99,"z":-50.63,"is_bot":false},{"t":282,"event":"Position","px":301,"py":549,"x":-105.02,"z":-55.4,"is_bot":false},{"t":287,"event":"Position","px":290,"py":542,"x":-114.75,"z":-49.31,"is_bot":false},{"t":291,"event":"Loot","px":294,"py":539,"x":-111.9,"z":-46.84,"is_bot":false},{"t":292,"event":"Position","px":291,"py":537,"x":-114.4,"z":-44.73,"is_bot":false},{"t":297,"event":"Position","px":289,"py":525,"x":-115.74,"z":-34.2,"is_bot":false},{"t":302,"event":"BotKill","px":291,"py":524,"x":-114.07,"z":-33.5,"is_bot":false},{"t":302,"event":"Position","px":291,"py":524,"x":-114.07,"z":-33.5,"is_bot":false},{"t":306,"event":"Loot","px":290,"py":526,"x":-115.51,"z":-35.18,"is_bot":false},{"t":307,"event":"Loot","px":290,"py":526,"x":-115.51,"z":-35.18,"is_bot":false},{"t":307,"event":"Position","px":289,"py":526,"x":-115.58,"z":-35.32,"is_bot":false},{"t":312,"event":"Loot","px":293,"py":527,"x":-112.42,"z":-36.17,"is_bot":false},{"t":312,"event":"Position","px":293,"py":527,"x":-112.42,"z":-36.17,"is_bot":false},{"t":322,"event":"Position","px":308,"py":530,"x":-99.62,"z":-39.1,"is_bot":false},{"t":322,"event":"Loot","px":308,"py":530,"x":-99.62,"z":-39.1,"is_bot":false},{"t":327,"event":"Loot","px":307,"py":528,"x":-100.47,"z":-36.85,"is_bot":false},{"t":327,"event":"Position","px":306,"py":528,"x":-100.76,"z":-36.72,"is_bot":false},{"t":337,"event":"Position","px":306,"py":533,"x":-100.63,"z":-41.89,"is_bot":false},{"t":339,"event":"Loot","px":306,"py":533,"x":-100.63,"z":-41.89,"is_bot":false},{"t":341,"event":"Loot","px":305,"py":539,"x":-102.03,"z":-46.91,"is_bot":false},{"t":342,"event":"Position","px":305,"py":539,"x":-102.03,"z":-46.91,"is_bot":false},{"t":347,"event":"Position","px":304,"py":536,"x":-102.68,"z":-43.84,"is_bot":false},{"t":352,"event":"Position","px":331,"py":548,"x":-79.37,"z":-54.32,"is_bot":false},{"t":357,"event":"Position","px":333,"py":551,"x":-77.01,"z":-57.45,"is_bot":false},{"t":360,"event":"Loot","px":332,"py":551,"x":-78.46,"z":-57.43,"is_bot":false},{"t":368,"event":"Position","px":341,"py":555,"x":-70.56,"z":-60.39,"is_bot":false},{"t":373,"event":"Position","px":363,"py":563,"x":-51.33,"z":-67.8,"is_bot":false},{"t":378,"event":"Position","px":378,"py":545,"x":-37.64,"z":-51.6,"is_bot":false},{"t":388,"event":"Position","px":387,"py":538,"x":-29.79,"z":-45.56,"is_bot":false},{"t":393,"event":"Position","px":390,"py":531,"x":-27.5,"z":-39.45,"is_bot":false},{"t":395,"event":"Loot","px":391,"py":529,"x":-26.06,"z":-38.07,"is_bot":false},{"t":403,"event":"Position","px":396,"py":511,"x":-21.55,"z":-22.3,"is_bot":false},{"t":407,"event":"BotKill","px":398,"py":503,"x":-19.95,"z":-15.18,"is_bot":false},{"t":408,"event":"Position","px":398,"py":503,"x":-19.89,"z":-15.09,"is_bot":false},{"t":413,"event":"Position","px":400,"py":499,"x":-18.51,"z":-11.97,"is_bot":false},{"t":413,"event":"Loot","px":400,"py":499,"x":-18.46,"z":-11.85,"is_bot":false},{"t":414,"event":"Loot","px":400,"py":499,"x":-18.46,"z":-11.85,"is_bot":false},{"t":418,"event":"Position","px":392,"py":510,"x":-25.31,"z":-20.97,"is_bot":false},{"t":422,"event":"Loot","px":388,"py":505,"x":-29.12,"z":-17.12,"is_bot":false},{"t":423,"event":"Position","px":388,"py":505,"x":-29.12,"z":-17.12,"is_bot":false},{"t":423,"event":"Loot","px":388,"py":505,"x":-29.12,"z":-17.12,"is_bot":false},{"t":426,"event":"Loot","px":388,"py":505,"x":-29.33,"z":-16.64,"is_bot":false},{"t":435,"event":"Loot","px":388,"py":505,"x":-29.33,"z":-16.64,"is_bot":false},{"t":438,"event":"Position","px":394,"py":506,"x":-23.57,"z":-17.5,"is_bot":false},{"t":443,"event":"Position","px":397,"py":482,"x":-21.19,"z":3.61,"is_bot":false},{"t":448,"event":"Position","px":387,"py":478,"x":-29.89,"z":6.45,"is_bot":false},{"t":453,"event":"Position","px":403,"py":472,"x":-16.02,"z":12.36,"is_bot":false},{"t":463,"event":"Position","px":415,"py":446,"x":-5.04,"z":35.23,"is_bot":false},{"t":468,"event":"Position","px":432,"py":400,"x":9.78,"z":75.53,"is_bot":false},{"t":473,"event":"Position","px":437,"py":368,"x":14.11,"z":103.59,"is_bot":false},{"t":478,"event":"Position","px":433,"py":363,"x":10.24,"z":107.82,"is_bot":false},{"t":488,"event":"Position","px":436,"py":367,"x":13.31,"z":104.75,"is_bot":false},{"t":498,"event":"Position","px":447,"py":346,"x":23.28,"z":123.3,"is_bot":false},{"t":503,"event":"Position","px":471,"py":330,"x":44.12,"z":137.02,"is_bot":false},{"t":508,"event":"Position","px":499,"py":328,"x":69.01,"z":138.58,"is_bot":false},{"t":513,"event":"Position","px":518,"py":337,"x":84.93,"z":130.85,"is_bot":false},{"t":518,"event":"Position","px":526,"py":335,"x":92.67,"z":132.48,"is_bot":false},{"t":523,"event":"Position","px":556,"py":332,"x":118.35,"z":134.93,"is_bot":false},{"t":528,"event":"Position","px":585,"py":329,"x":143.73,"z":137.66,"is_bot":false},{"t":533,"event":"Position","px":612,"py":324,"x":168.0,"z":141.94,"is_bot":false},{"t":538,"event":"Position","px":632,"py":319,"x":185.51,"z":146.36,"is_bot":false},{"t":543,"event":"Position","px":649,"py":299,"x":200.08,"z":164.62,"is_bot":false},{"t":549,"event":"Position","px":664,"py":275,"x":213.74,"z":185.25,"is_bot":false},{"t":554,"event":"Position","px":667,"py":273,"x":216.24,"z":187.0,"is_bot":false}]