[{"t":0,"event":"Position","px":303,"py":901,"x":-103.55,"z":-365.2,"is_bot":false},{"t":15,"event":"Position","px":315,"py":889,"x":-93.14,"z":-354.08,"is_bot":false},{"t":20,"event":"Position","px":344,"py":875,"x":-67.49,"z":-341.95,"is_bot":false},{"t":25,"event":"Position","px":353,"py":892,"x":-59.81,"z":-357.02,"is_bot":false},{"t":35,"event":"Position","px":359,"py":893,"x":-54.26,"z":-357.56,"is_bot":false},{"t":39,"event":"Loot","px":361,"py":893,"x":-52.76,"z":-357.74,"is_bot":false},{"t":41,"event":"Loot","px":361,"py":894,"x":-52.59,"z":-359.05,"is_bot":false},{"t":45,"event":"Position","px":369,"py":882,"x":-45.61,"z":-348.63,"is_bot":false},{"t":50,"event":"Position","px":372,"py":896,"x":-43.34,"z":-360.23,"is_bot":false},{"t":52,"event":"Loot","px":373,"py":895,"x":-42.07,"z":-359.28,"is_bot":false},{"t":53,"event":"Loot","px":375,"py":895,"x":-40.81,"z":-359.54,"is_bot":false},{"t":55,"event":"Position","px":375,"py":895,"x":-40.81,"z":-359.54,"is_bot":false},{"t":60,"event":"Position","px":370,"py":896,"x":-45.02,"z":-360.39,"is_bot":false},{"t":65,"event":"Position","px":371,"py":898,"x":-43.71,"z":-362.65,"is_bot":false},{"t":70,"event":"Position","px":390,"py":904,"x":-26.96,"z":-367.34,"is_bot":false},{"t":75,"event":"Position","px":397,"py":874,"x":-21.27,"z":-340.85,"is_bot":false},{"t":80,"event":"Position","px":408,"py":844,"x":-11.73,"z":-314.75,"is_bot":false},{"t":85,"event":"Position","px":418,"py":813,"x":-2.62,"z":-287.19,"is_bot":false},{"t":88,"event":"Loot","px":416,"py":799,"x":-4.13,"z":-275.1,"is_bot":false},{"t":90,"event":"Position","px":420,"py":800,"x":-1.25,"z":-275.91,"is_bot":false},{"t":92,"event":"Loot","px":420,"py":800,"x":-0.49,"z":-276.53,"is_bot":false},{"t":100,"event":"Position","px":412,"py":817,"x":-8.27,"z":-291.28,"is_bot":false},{"t":105,"event":"Position","px":421,"py":799,"x":-0.03,"z":-275.27,"is_bot":false},{"t":110,"event":"Position","px":449,"py":806,"x":24.85,"z":-281.82,"is_bot":false},{"t":115,"event":"Position","px":450,"py":809,"x":25.1,"z":-284.01,"is_bot":false},{"t":119,"event":"BotKill","px":439,"py":807,"x":16.13,"z":-282.07,"is_bot":false},{"t":120,"event":"Position","px":437,"py":808,"x":13.66,"z":-283.01,"is_bot":false},{"t":124,"event":"Loot","px":451,"py":804,"x":26.78,"z":-279.23,"is_bot":false},{"t":125,"event":"Loot","px":451,"py":804,"x":26.78,"z":-279.23,"is_bot":false},{"t":125,"event":"Position","px":451,"py":804,"x":26.78,"z":-279.23,"is_bot":false},{"t":130,"event":"Position","px":437,"py":823,"x":14.47,"z":-296.65,"is_bot":false},{"t":135,"event":"Position","px":435,"py":808,"x":12.72,"z":-283.5,"is_bot":false},{"t":140,"event":"Position","px":450,"py":794,"x":25.56,"z":-271.16,"is_bot":false},{"t":145,"event":"Position","px":422,"py":798,"x":1.29,"z":-274.0,"is_bot":false},{"t":150,"event":"Position","px":415,"py":807,"x":-4.82,"z":-282.15,"is_bot":false},{"t":156,"event":"Position","px":408,"py":803,"x":-11.39,"z":-278.88,"is_bot":false},{"t":161,"event":"Position","px":416,"py":809,"x":-4.1,"z":-284.26,"is_bot":false},{"t":166,"event":"Position","px":418,"py":811,"x":-2.58,"z":-285.7,"is_bot":false},{"t":171,"event":"Position","px":411,"py":808,"x":-8.44,"z":-283.16,"is_bot":false},{"t":176,"event":"Position","px":416,"py":802,"x":-4.18,"z":-277.54,"is_bot":false},{"t":181,"event":"Position","px":419,"py":804,"x":-2.11,"z":-280.01,"is_bot":false},{"t":186,"event":"Position","px":416,"py":795,"x":-4.67,"z":-271.99,"is_bot":false},{"t":191,"event":"Position","px":400,"py":803,"x":-18.12,"z":-278.45,"is_bot":false},{"t":191,"event":"Loot","px":400,"py":803,"x":-18.1,"z":-278.72,"is_bot":false},{"t":196,"event":"Position","px":403,"py":799,"x":-15.81,"z":-274.92,"is_bot":false},{"t":201,"event":"Position","px":412,"py":794,"x":-8.18,"z":-271.1,"is_bot":false},{"t":206,"event":"Position","px":424,"py":779,"x":2.23,"z":-257.93,"is_bot":false},{"t":211,"event":"Position","px":418,"py":793,"x":-2.6,"z":-270.01,"is_bot":false},{"t":216,"event":"Position","px":408,"py":800,"x":-11.29,"z":-276.54,"is_bot":false},{"t":221,"event":"Position","px":418,"py":813,"x":-2.97,"z":-287.33,"is_bot":false},{"t":226,"event":"Position","px":423,"py":828,"x":2.15,"z":-300.3,"is_bot":false},{"t":246,"event":"Position","px":426,"py":827,"x":4.13,"z":-299.96,"is_bot":false},{"t":251,"event":"Position","px":433,"py":823,"x":10.68,"z":-296.64,"is_bot":false},{"t":256,"event":"Position","px":443,"py":850,"x":19.11,"z":-320.19,"is_bot":false},{"t":261,"event":"Position","px":420,"py":840,"x":-1.0,"z":-311.0,"is_bot":false},{"t":266,"event":"Position","px":425,"py":840,"x":3.54,"z":-311.3,"is_bot":false},{"t":271,"event":"Position","px":437,"py":839,"x":13.9,"z":-310.66,"is_bot":false},{"t":271,"event":"BotKill","px":437,"py":839,"x":13.9,"z":-310.66,"is_bot":false},{"t":273,"event":"Loot","px":436,"py":839,"x":13.48,"z":-310.37,"is_bot":false},{"t":281,"event":"Position","px":448,"py":836,"x":23.74,"z":-307.73,"is_bot":false},{"t":286,"event":"Position","px":438,"py":827,"x":14.74,"z":-299.99,"is_bot":false},{"t":291,"event":"Position","px":425,"py":819,"x":3.64,"z":-292.76,"is_bot":false},{"t":296,"event":"Position","px":422,"py":826,"x":0.97,"z":-299.3,"is_bot":false},{"t":301,"event":"Position","px":418,"py":824,"x":-2.57,"z":-297.18,"is_bot":false},{"t":311,"event":"BotKilled","px":415,"py":818,"x":-5.48,"z":-291.86,"is_bot":false},{"t":311,"event":"Position","px":415,"py":818,"x":-5.45,"z":-291.83,"is_bot":false}]