[{"t":0,"event":"Position","px":223,"py":106,"x":-174.38,"z":333.86,"is_bot":false},{"t":10,"event":"Position","px":237,"py":124,"x":-161.65,"z":317.61,"is_bot":false},{"t":15,"event":"Position","px":247,"py":141,"x":-153.22,"z":302.69,"is_bot":false},{"t":17,"event":"Loot","px":247,"py":141,"x":-153.22,"z":302.69,"is_bot":false},{"t":17,"event":"Loot","px":247,"py":141,"x":-153.22,"z":302.69,"is_bot":false},{"t":18,"event":"Loot","px":247,"py":141,"x":-153.22,"z":302.69,"is_bot":false},{"t":20,"event":"Position","px":246,"py":145,"x":-153.79,"z":299.72,"is_bot":false},{"t":22,"event":"Loot","px":243,"py":146,"x":-156.25,"z":299.07,"is_bot":false},{"t":25,"event":"Position","px":239,"py":149,"x":-160.35,"z":295.94,"is_bot":false},{"t":25,"event":"Loot","px":239,"py":149,"x":-160.35,"z":295.94,"is_bot":false},{"t":27,"event":"Loot","px":238,"py":148,"x":-160.66,"z":297.25,"is_bot":false},{"t":30,"event":"Position","px":244,"py":151,"x":-155.15,"z":294.69,"is_bot":false},{"t":34,"event":"Loot","px":253,"py":146,"x":-147.46,"z":298.31,"is_bot":false},{"t":35,"event":"Position","px":252,"py":145,"x":-148.48,"z":299.71,"is_bot":false},{"t":40,"event":"Position","px":257,"py":147,"x":-144.07,"z":298.01,"is_bot":false},{"t":45,"event":"Position","px":254,"py":164,"x":-146.75,"z":283.11,"is_bot":false},{"t":50,"event":"Position","px":264,"py":195,"x":-137.73,"z":255.95,"is_bot":false},{"t":55,"event":"Position","px":278,"py":202,"x":-125.73,"z":249.53,"is_bot":false},{"t":57,"event":"Loot","px":278,"py":202,"x":-125.94,"z":249.32,"is_bot":false},{"t":60,"event":"Position","px":283,"py":203,"x":-120.91,"z":248.64,"is_bot":false},{"t":65,"event":"Position","px":283,"py":233,"x":-121.25,"z":222.26,"is_bot":false},{"t":70,"event":"Position","px":305,"py":258,"x":-102.11,"z":200.43,"is_bot":false},{"t":75,"event":"Position","px":322,"py":272,"x":-87.06,"z":188.31,"is_bot":false},{"t":80,"event":"Position","px":303,"py":285,"x":-103.29,"z":176.08,"is_bot":false},{"t":85,"event":"Position","px":295,"py":313,"x":-110.64,"z":151.65,"is_bot":false},{"t":90,"event":"Position","px":293,"py":343,"x":-112.86,"z":125.73,"is_bot":false},{"t":95,"event":"Position","px":301,"py":365,"x":-105.82,"z":105.8,"is_bot":false},{"t":100,"event":"Position","px":298,"py":377,"x":-108.32,"z":95.34,"is_bot":false},{"t":102,"event":"Loot","px":298,"py":377,"x":-108.32,"z":95.34,"is_bot":false},{"t":105,"event":"Position","px":306,"py":377,"x":-101.18,"z":95.58,"is_bot":false},{"t":110,"event":"Position","px":309,"py":401,"x":-98.01,"z":74.49,"is_bot":false},{"t":115,"event":"Position","px":332,"py":397,"x":-77.99,"z":77.83,"is_bot":false},{"t":117,"event":"Loot","px":343,"py":390,"x":-68.62,"z":84.08,"is_bot":false},{"t":120,"event":"Position","px":345,"py":386,"x":-67.1,"z":87.36,"is_bot":false},{"t":125,"event":"Position","px":350,"py":395,"x":-62.23,"z":79.97,"is_bot":false},{"t":130,"event":"Position","px":354,"py":406,"x":-58.98,"z":69.93,"is_bot":false},{"t":135,"event":"Position","px":334,"py":401,"x":-76.26,"z":74.47,"is_bot":false},{"t":140,"event":"Position","px":329,"py":398,"x":-80.65,"z":77.09,"is_bot":false},{"t":142,"event":"BotKill","px":329,"py":402,"x":-80.52,"z":73.98,"is_bot":false},{"t":145,"event":"Position","px":330,"py":416,"x":-79.9,"z":61.43,"is_bot":false},{"t":146,"event":"Loot","px":330,"py":416,"x":-79.9,"z":61.43,"is_bot":false},{"t":146,"event":"Loot","px":330,"py":416,"x":-79.9,"z":61.43,"is_bot":false},{"t":150,"event":"Position","px":329,"py":420,"x":-80.74,"z":58.15,"is_bot":false},{"t":155,"event":"Position","px":315,"py":425,"x":-93.31,"z":53.19,"is_bot":false},{"t":158,"event":"BotKill","px":313,"py":437,"x":-94.46,"z":42.55,"is_bot":false},{"t":160,"event":"Position","px":317,"py":441,"x":-91.16,"z":39.76,"is_bot":false},{"t":167,"event":"Loot","px":314,"py":440,"x":-94.15,"z":40.17,"is_bot":false},{"t":167,"event":"Loot","px":314,"py":440,"x":-94.15,"z":40.17,"is_bot":false},{"t":170,"event":"Position","px":312,"py":441,"x":-95.89,"z":39.2,"is_bot":false},{"t":173,"event":"Loot","px":309,"py":451,"x":-98.75,"z":30.3,"is_bot":false},{"t":176,"event":"Position","px":308,"py":451,"x":-99.22,"z":30.34,"is_bot":false},{"t":186,"event":"Position","px":309,"py":463,"x":-98.08,"z":20.19,"is_bot":false},{"t":189,"event":"Loot","px":309,"py":463,"x":-98.08,"z":20.19,"is_bot":false},{"t":196,"event":"Position","px":295,"py":446,"x":-110.47,"z":34.91,"is_bot":false},{"t":198,"event":"Loot","px":296,"py":446,"x":-110.27,"z":35.36,"is_bot":false},{"t":201,"event":"Position","px":287,"py":443,"x":-118.14,"z":37.85,"is_bot":false},{"t":206,"event":"Position","px":278,"py":438,"x":-125.76,"z":42.33,"is_bot":false},{"t":206,"event":"Loot","px":278,"py":438,"x":-125.76,"z":42.33,"is_bot":false},{"t":211,"event":"Position","px":280,"py":458,"x":-124.34,"z":24.17,"is_bot":false},{"t":216,"event":"Position","px":279,"py":483,"x":-125.1,"z":2.2,"is_bot":false},{"t":219,"event":"Loot","px":284,"py":492,"x":-120.38,"z":-5.16,"is_bot":false},{"t":221,"event":"Position","px":286,"py":492,"x":-118.27,"z":-5.8,"is_bot":false},{"t":226,"event":"Position","px":294,"py":502,"x":-111.46,"z":-13.96,"is_bot":false},{"t":231,"event":"Position","px":290,"py":525,"x":-115.4,"z":-34.28,"is_bot":false},{"t":233,"event":"Loot","px":292,"py":526,"x":-113.68,"z":-35.03,"is_bot":false},{"t":236,"event":"Position","px":297,"py":537,"x":-109.35,"z":-44.6,"is_bot":false},{"t":237,"event":"Loot","px":295,"py":538,"x":-110.64,"z":-45.97,"is_bot":false},{"t":241,"event":"Position","px":301,"py":527,"x":-105.71,"z":-36.08,"is_bot":false},{"t":245,"event":"Loot","px":306,"py":539,"x":-100.93,"z":-46.4,"is_bot":false},{"t":246,"event":"Position","px":306,"py":538,"x":-101.4,"z":-46.28,"is_bot":false},{"t":251,"event":"Position","px":301,"py":538,"x":-105.12,"z":-46.19,"is_bot":false},{"t":256,"event":"Position","px":290,"py":543,"x":-115.47,"z":-50.17,"is_bot":false},{"t":261,"event":"Position","px":278,"py":568,"x":-125.63,"z":-71.92,"is_bot":false},{"t":266,"event":"Position","px":265,"py":594,"x":-136.68,"z":-94.86,"is_bot":false},{"t":271,"event":"Position","px":257,"py":626,"x":-144.17,"z":-123.12,"is_bot":false},{"t":276,"event":"Position","px":238,"py":650,"x":-160.74,"z":-144.56,"is_bot":false},{"t":280,"event":"Loot","px":233,"py":658,"x":-164.92,"z":-151.14,"is_bot":false},{"t":281,"event":"Position","px":234,"py":663,"x":-163.98,"z":-155.53,"is_bot":false},{"t":286,"event":"Position","px":232,"py":688,"x":-166.43,"z":-178.13,"is_bot":false},{"t":291,"event":"Position","px":228,"py":718,"x":-169.94,"z":-204.09,"is_bot":false},{"t":296,"event":"Position","px":232,"py":742,"x":-165.76,"z":-225.31,"is_bot":false},{"t":300,"event":"Loot","px":234,"py":746,"x":-163.93,"z":-228.44,"is_bot":false},{"t":301,"event":"Position","px":235,"py":751,"x":-163.06,"z":-233.04,"is_bot":false},{"t":306,"event":"Loot","px":236,"py":767,"x":-162.29,"z":-247.55,"is_bot":false},{"t":306,"event":"Position","px":236,"py":767,"x":-162.29,"z":-247.55,"is_bot":false},{"t":311,"event":"Position","px":258,"py":758,"x":-143.15,"z":-239.58,"is_bot":false},{"t":316,"event":"Loot","px":258,"py":757,"x":-142.84,"z":-238.73,"is_bot":false},{"t":321,"event":"Position","px":281,"py":761,"x":-122.76,"z":-241.44,"is_bot":false},{"t":326,"event":"Position","px":290,"py":774,"x":-114.96,"z":-253.47,"is_bot":false},{"t":331,"event":"Position","px":304,"py":796,"x":-102.81,"z":-272.69,"is_bot":false},{"t":336,"event":"Position","px":310,"py":814,"x":-97.87,"z":-288.6,"is_bot":false},{"t":338,"event":"Loot","px":306,"py":812,"x":-101.05,"z":-286.52,"is_bot":false},{"t":341,"event":"Position","px":307,"py":829,"x":-100.26,"z":-301.31,"is_bot":false},{"t":346,"event":"Position","px":319,"py":855,"x":-89.65,"z":-324.33,"is_bot":false},{"t":352,"event":"Position","px":346,"py":874,"x":-65.62,"z":-341.43,"is_bot":false},{"t":357,"event":"Position","px":356,"py":892,"x":-56.93,"z":-357.24,"is_bot":false},{"t":359,"event":"Loot","px":361,"py":894,"x":-52.67,"z":-358.92,"is_bot":false},{"t":362,"event":"Position","px":361,"py":893,"x":-52.77,"z":-357.46,"is_bot":false},{"t":363,"event":"Loot","px":361,"py":893,"x":-52.77,"z":-357.46,"is_bot":false},{"t":363,"event":"Loot","px":361,"py":893,"x":-52.77,"z":-357.46,"is_bot":false},{"t":367,"event":"Position","px":361,"py":886,"x":-52.76,"z":-352.04,"is_bot":false},{"t":368,"event":"Loot","px":359,"py":889,"x":-54.3,"z":-354.68,"is_bot":false},{"t":372,"event":"Position","px":366,"py":885,"x":-48.57,"z":-351.11,"is_bot":false},{"t":374,"event":"Loot","px":374,"py":895,"x":-40.91,"z":-359.54,"is_bot":false},{"t":377,"event":"Position","px":373,"py":895,"x":-41.89,"z":-359.48,"is_bot":false},{"t":384,"event":"Loot","px":373,"py":895,"x":-41.89,"z":-359.48,"is_bot":false},{"t":390,"event":"Loot","px":371,"py":889,"x":-43.65,"z":-354.13,"is_bot":false},{"t":392,"event":"Position","px":369,"py":891,"x":-45.51,"z":-356.2,"is_bot":false},{"t":397,"event":"Position","px":365,"py":874,"x":-49.18,"z":-341.27,"is_bot":false},{"t":402,"event":"Position","px":384,"py":884,"x":-32.45,"z":-349.56,"is_bot":false},{"t":407,"event":"Loot","px":382,"py":894,"x":-34.68,"z":-358.49,"is_bot":false},{"t":407,"event":"Position","px":382,"py":894,"x":-34.68,"z":-358.49,"is_bot":false},{"t":412,"event":"Position","px":380,"py":902,"x":-36.27,"z":-365.54,"is_bot":false},{"t":417,"event":"Position","px":348,"py":903,"x":-64.14,"z":-366.39,"is_bot":false},{"t":422,"event":"Position","px":317,"py":904,"x":-91.16,"z":-367.91,"is_bot":false},{"t":427,"event":"Position","px":282,"py":903,"x":-121.82,"z":-366.95,"is_bot":false},{"t":432,"event":"Position","px":258,"py":896,"x":-143.2,"z":-360.51,"is_bot":false},{"t":437,"event":"Position","px":246,"py":892,"x":-153.48,"z":-356.76,"is_bot":false},{"t":442,"event":"Position","px":218,"py":881,"x":-178.64,"z":-347.18,"is_bot":false},{"t":446,"event":"Loot","px":219,"py":869,"x":-177.18,"z":-336.75,"is_bot":false},{"t":447,"event":"Position","px":219,"py":869,"x":-177.74,"z":-337.19,"is_bot":false},{"t":452,"event":"Loot","px":204,"py":851,"x":-190.7,"z":-321.35,"is_bot":false},{"t":452,"event":"Position","px":204,"py":851,"x":-190.7,"z":-321.35,"is_bot":false},{"t":453,"event":"Loot","px":204,"py":851,"x":-190.7,"z":-321.35,"is_bot":false},{"t":457,"event":"Position","px":205,"py":849,"x":-189.79,"z":-319.07,"is_bot":false},{"t":462,"event":"Position","px":196,"py":841,"x":-197.73,"z":-312.09,"is_bot":false},{"t":472,"event":"Position","px":186,"py":849,"x":-206.91,"z":-319.57,"is_bot":false},{"t":476,"event":"Loot","px":203,"py":848,"x":-191.25,"z":-318.55,"is_bot":false},{"t":477,"event":"Position","px":203,"py":846,"x":-191.98,"z":-316.73,"is_bot":false},{"t":482,"event":"Position","px":225,"py":838,"x":-172.28,"z":-309.62,"is_bot":false},{"t":487,"event":"Position","px":258,"py":829,"x":-143.46,"z":-301.92,"is_bot":false},{"t":492,"event":"Position","px":280,"py":805,"x":-123.94,"z":-280.76,"is_bot":false},{"t":497,"event":"Position","px":277,"py":781,"x":-126.95,"z":-259.07,"is_bot":false},{"t":522,"event":"Position","px":294,"py":778,"x":-111.89,"z":-256.86,"is_bot":false},{"t":527,"event":"Position","px":311,"py":801,"x":-97.0,"z":-277.11,"is_bot":false},{"t":533,"event":"Position","px":341,"py":808,"x":-70.51,"z":-283.42,"is_bot":false},{"t":538,"event":"Position","px":373,"py":795,"x":-42.52,"z":-271.91,"is_bot":false},{"t":543,"event":"Position","px":395,"py":771,"x":-23.02,"z":-251.01,"is_bot":false},{"t":548,"event":"Position","px":397,"py":747,"x":-21.06,"z":-229.46,"is_bot":false},{"t":553,"event":"Position","px":404,"py":712,"x":-15.06,"z":-198.46,"is_bot":false},{"t":558,"event":"Position","px":414,"py":689,"x":-6.52,"z":-178.55,"is_bot":false},{"t":563,"event":"Position","px":429,"py":656,"x":6.9,"z":-149.19,"is_bot":false},{"t":568,"event":"Position","px":443,"py":635,"x":19.48,"z":-131.33,"is_bot":false},{"t":578,"event":"Position","px":428,"py":654,"x":5.75,"z":-148.12,"is_bot":false},{"t":583,"event":"Position","px":430,"py":667,"x":7.82,"z":-159.4,"is_bot":false},{"t":588,"event":"Position","px":444,"py":689,"x":19.96,"z":-178.17,"is_bot":false},{"t":593,"event":"Position","px":457,"py":713,"x":31.94,"z":-199.78,"is_bot":false},{"t":598,"event":"Position","px":466,"py":739,"x":39.65,"z":-222.08,"is_bot":false},{"t":603,"event":"Position","px":451,"py":766,"x":26.35,"z":-246.2,"is_bot":false},{"t":608,"event":"Position","px":450,"py":799,"x":25.3,"z":-275.39,"is_bot":false},{"t":613,"event":"Position","px":451,"py":821,"x":26.6,"z":-294.77,"is_bot":false},{"t":618,"event":"Position","px":478,"py":837,"x":49.96,"z":-308.73,"is_bot":false},{"t":623,"event":"Position","px":490,"py":854,"x":60.58,"z":-323.2,"is_bot":false},{"t":625,"event":"Loot","px":491,"py":854,"x":61.21,"z":-323.17,"is_bot":false},{"t":628,"event":"Position","px":480,"py":862,"x":51.79,"z":-330.21,"is_bot":false},{"t":629,"event":"Loot","px":476,"py":862,"x":48.25,"z":-330.96,"is_bot":false},{"t":633,"event":"Position","px":474,"py":851,"x":46.33,"z":-321.22,"is_bot":false},{"t":638,"event":"Position","px":480,"py":860,"x":51.69,"z":-328.82,"is_bot":false},{"t":643,"event":"Position","px":470,"py":853,"x":43.19,"z":-322.71,"is_bot":false},{"t":648,"event":"Position","px":489,"py":852,"x":59.57,"z":-321.45,"is_bot":false},{"t":653,"event":"Position","px":494,"py":844,"x":64.05,"z":-315.12,"is_bot":false},{"t":658,"event":"Position","px":500,"py":837,"x":69.52,"z":-308.75,"is_bot":false}]