[{"t":0,"event":"Position","px":149,"py":641,"x":-354.13,"z":-125.93,"is_bot":false},{"t":5,"event":"BotPosition","px":716,"py":312,"x":199.25,"z":195.8,"is_bot":true},{"t":5,"event":"BotPosition","px":169,"py":389,"x":-335.36,"z":120.01,"is_bot":true},{"t":5,"event":"BotPosition","px":778,"py":556,"x":260.08,"z":-43.43,"is_bot":true},{"t":5,"event":"BotPosition","px":259,"py":330,"x":-247.5,"z":177.33,"is_bot":true},{"t":5,"event":"BotPosition","px":863,"py":389,"x":342.3,"z":120.53,"is_bot":true},{"t":5,"event":"BotPosition","px":325,"py":759,"x":-182.65,"z":-240.87,"is_bot":true},{"t":5,"event":"BotPosition","px":642,"py":200,"x":126.69,"z":304.48,"is_bot":true},{"t":11,"event":"BotPosition","px":704,"py":328,"x":187.69,"z":179.69,"is_bot":true},{"t":11,"event":"BotPosition","px":185,"py":400,"x":-319.8,"z":109.81,"is_bot":true},{"t":11,"event":"BotPosition","px":782,"py":552,"x":263.91,"z":-39.11,"is_bot":true},{"t":11,"event":"BotPosition","px":240,"py":346,"x":-265.74,"z":161.95,"is_bot":true},{"t":11,"event":"BotPosition","px":841,"py":381,"x":321.13,"z":127.56,"is_bot":true},{"t":11,"event":"BotPosition","px":334,"py":738,"x":-173.99,"z":-220.97,"is_bot":true},{"t":11,"event":"BotPosition","px":639,"py":214,"x":123.99,"z":290.99,"is_bot":true},{"t":16,"event":"BotPosition","px":690,"py":339,"x":173.94,"z":169.04,"is_bot":true},{"t":16,"event":"BotPosition","px":191,"py":412,"x":-313.12,"z":98.05,"is_bot":true},{"t":16,"event":"BotPosition","px":795,"py":538,"x":276.44,"z":-25.72,"is_bot":true},{"t":16,"event":"BotPosition","px":231,"py":369,"x":-274.17,"z":139.57,"is_bot":true},{"t":16,"event":"BotPosition","px":817,"py":388,"x":297.88,"z":121.37,"is_bot":true},{"t":16,"event":"BotPosition","px":347,"py":718,"x":-160.97,"z":-200.76,"is_bot":true},{"t":16,"event":"BotPosition","px":639,"py":239,"x":124.48,"z":266.58,"is_bot":true},{"t":21,"event":"BotPosition","px":689,"py":353,"x":172.95,"z":155.16,"is_bot":true},{"t":21,"event":"BotPosition","px":201,"py":422,"x":-303.37,"z":88.02,"is_bot":true},{"t":21,"event":"BotPosition","px":787,"py":528,"x":268.48,"z":-15.33,"is_bot":true},{"t":21,"event":"BotPosition","px":237,"py":384,"x":-268.94,"z":125.04,"is_bot":true},{"t":21,"event":"BotPosition","px":803,"py":404,"x":284.41,"z":105.09,"is_bot":true},{"t":21,"event":"BotPosition","px":351,"py":698,"x":-157.43,"z":-181.64,"is_bot":true},{"t":21,"event":"BotPosition","px":634,"py":262,"x":119.44,"z":244.05,"is_bot":true},{"t":21,"event":"Position","px":170,"py":627,"x":-333.57,"z":-112.11,"is_bot":false},{"t":26,"event":"BotPosition","px":673,"py":364,"x":157.52,"z":144.27,"is_bot":true},{"t":26,"event":"BotPosition","px":217,"py":436,"x":-288.33,"z":74.31,"is_bot":true},{"t":26,"event":"BotPosition","px":762,"py":530,"x":244.57,"z":-17.63,"is_bot":true},{"t":26,"event":"BotPosition","px":260,"py":376,"x":-245.92,"z":132.99,"is_bot":true},{"t":26,"event":"BotPosition","px":794,"py":427,"x":275.83,"z":82.68,"is_bot":true},{"t":26,"event":"BotPosition","px":348,"py":673,"x":-160.38,"z":-157.29,"is_bot":true},{"t":26,"event":"BotPosition","px":619,"py":276,"x":104.64,"z":230.23,"is_bot":true},{"t":26,"event":"Position","px":190,"py":617,"x":-314.77,"z":-102.06,"is_bot":false},{"t":31,"event":"BotPosition","px":660,"py":384,"x":144.92,"z":124.72,"is_bot":true},{"t":31,"event":"BotPosition","px":230,"py":451,"x":-275.43,"z":60.01,"is_bot":true},{"t":31,"event":"BotPosition","px":745,"py":537,"x":227.83,"z":-24.75,"is_bot":true},{"t":31,"event":"BotPosition","px":265,"py":375,"x":-241.08,"z":134.25,"is_bot":true},{"t":31,"event":"BotPosition","px":791,"py":435,"x":272.01,"z":75.56,"is_bot":true},{"t":31,"event":"BotPosition","px":337,"py":655,"x":-170.56,"z":-139.83,"is_bot":true},{"t":31,"event":"BotPosition","px":601,"py":275,"x":86.69,"z":231.74,"is_bot":true},{"t":31,"event":"Position","px":201,"py":608,"x":-303.26,"z":-94.1,"is_bot":false},{"t":36,"event":"BotPosition","px":646,"py":400,"x":130.61,"z":109.24,"is_bot":true},{"t":36,"event":"BotPosition","px":243,"py":461,"x":-263.0,"z":49.67,"is_bot":true},{"t":36,"event":"BotPosition","px":769,"py":547,"x":250.6,"z":-33.96,"is_bot":true},{"t":36,"event":"BotPosition","px":248,"py":390,"x":-257.5,"z":119.53,"is_bot":true},{"t":36,"event":"BotPosition","px":770,"py":420,"x":252.25,"z":90.31,"is_bot":true},{"t":36,"event":"BotPosition","px":314,"py":650,"x":-193.21,"z":-134.91,"is_bot":true},{"t":36,"event":"BotPosition","px":594,"py":257,"x":79.59,"z":249.36,"is_bot":true},{"t":36,"event":"Position","px":209,"py":615,"x":-296.12,"z":-100.51,"is_bot":false},{"t":41,"event":"BotPosition","px":648,"py":409,"x":132.5,"z":101.02,"is_bot":true},{"t":41,"event":"BotPosition","px":225,"py":450,"x":-279.86,"z":60.63,"is_bot":true},{"t":41,"event":"BotPosition","px":774,"py":563,"x":256.07,"z":-50.11,"is_bot":true},{"t":41,"event":"BotPosition","px":237,"py":395,"x":-268.22,"z":114.02,"is_bot":true},{"t":41,"event":"BotPosition","px":756,"py":412,"x":238.67,"z":97.45,"is_bot":true},{"t":41,"event":"BotPosition","px":308,"py":642,"x":-199.34,"z":-127.21,"is_bot":true},{"t":41,"event":"BotPosition","px":585,"py":235,"x":70.87,"z":270.63,"is_bot":true},{"t":41,"event":"Position","px":216,"py":621,"x":-289.24,"z":-106.34,"is_bot":false},{"t":46,"event":"BotPosition","px":647,"py":425,"x":131.36,"z":84.97,"is_bot":true},{"t":46,"event":"BotPosition","px":228,"py":435,"x":-277.1,"z":75.4,"is_bot":true},{"t":46,"event":"BotPosition","px":756,"py":577,"x":238.57,"z":-63.43,"is_bot":true},{"t":46,"event":"BotPosition","px":227,"py":409,"x":-278.33,"z":100.98,"is_bot":true},{"t":46,"event":"BotPosition","px":759,"py":429,"x":241.05,"z":81.22,"is_bot":true},{"t":46,"event":"BotPosition","px":308,"py":623,"x":-199.17,"z":-108.46,"is_bot":true},{"t":46,"event":"BotPosition","px":593,"py":217,"x":78.91,"z":287.77,"is_bot":true},{"t":46,"event":"Position","px":211,"py":618,"x":-293.82,"z":-103.69,"is_bot":false},{"t":50,"event":"Loot","px":209,"py":616,"x":-295.69,"z":-101.27,"is_bot":false},{"t":51,"event":"BotPosition","px":625,"py":435,"x":110.79,"z":75.35,"is_bot":true},{"t":51,"event":"BotPosition","px":214,"py":432,"x":-291.4,"z":78.57,"is_bot":true},{"t":51,"event":"BotPosition","px":747,"py":579,"x":229.88,"z":-65.03,"is_bot":true},{"t":51,"event":"BotPosition","px":225,"py":421,"x":-280.5,"z":88.58,"is_bot":true},{"t":51,"event":"BotPosition","px":754,"py":436,"x":236.23,"z":73.75,"is_bot":true},{"t":51,"event":"BotPosition","px":310,"py":603,"x":-197.07,"z":-88.43,"is_bot":true},{"t":51,"event":"BotPosition","px":606,"py":211,"x":91.9,"z":294.38,"is_bot":true},{"t":51,"event":"Position","px":209,"py":616,"x":-295.69,"z":-101.27,"is_bot":false},{"t":56,"event":"BotPosition","px":607,"py":446,"x":92.74,"z":64.15,"is_bot":true},{"t":56,"event":"BotPosition","px":216,"py":415,"x":-289.36,"z":94.45,"is_bot":true},{"t":56,"event":"BotPosition","px":733,"py":562,"x":215.43,"z":-48.43,"is_bot":true},{"t":56,"event":"BotPosition","px":217,"py":435,"x":-287.79,"z":75.39,"is_bot":true},{"t":56,"event":"BotPosition","px":746,"py":430,"x":228.76,"z":79.92,"is_bot":true},{"t":56,"event":"BotPosition","px":300,"py":595,"x":-206.85,"z":-81.54,"is_bot":true},{"t":56,"event":"BotPosition","px":628,"py":206,"x":113.53,"z":298.95,"is_bot":true},{"t":56,"event":"Position","px":198,"py":620,"x":-306.84,"z":-105.3,"is_bot":false},{"t":59,"event":"Loot","px":198,"py":629,"x":-306.3,"z":-113.9,"is_bot":false},{"t":61,"event":"BotPosition","px":603,"py":460,"x":88.5,"z":50.99,"is_bot":true},{"t":61,"event":"BotPosition","px":201,"py":403,"x":-303.4,"z":106.46,"is_bot":true},{"t":61,"event":"BotPosition","px":714,"py":558,"x":197.05,"z":-44.77,"is_bot":true},{"t":61,"event":"BotPosition","px":229,"py":437,"x":-276.84,"z":73.38,"is_bot":true},{"t":61,"event":"BotPosition","px":725,"py":419,"x":207.67,"z":90.72,"is_bot":true},{"t":61,"event":"BotPosition","px":275,"py":593,"x":-231.11,"z":-78.81,"is_bot":true},{"t":61,"event":"BotPosition","px":640,"py":194,"x":124.73,"z":310.21,"is_bot":true},{"t":61,"event":"Position","px":199,"py":628,"x":-306.04,"z":-113.66,"is_bot":false},{"t":64,"event":"Loot","px":201,"py":627,"x":-303.81,"z":-112.66,"is_bot":false},{"t":66,"event":"BotPosition","px":593,"py":472,"x":79.2,"z":39.42,"is_bot":true},{"t":66,"event":"BotPosition","px":212,"py":384,"x":-293.03,"z":125.47,"is_bot":true},{"t":66,"event":"BotPosition","px":725,"py":547,"x":207.76,"z":-34.57,"is_bot":true},{"t":66,"event":"BotPosition","px":227,"py":417,"x":-278.66,"z":92.78,"is_bot":true},{"t":66,"event":"BotPosition","px":700,"py":414,"x":183.6,"z":95.77,"is_bot":true},{"t":66,"event":"BotPosition","px":253,"py":596,"x":-253.41,"z":-82.39,"is_bot":true},{"t":66,"event":"BotPosition","px":635,"py":217,"x":120.19,"z":288.1,"is_bot":true},{"t":66,"event":"Position","px":201,"py":627,"x":-303.81,"z":-112.66,"is_bot":false},{"t":71,"event":"BotPosition","px":591,"py":474,"x":77.34,"z":37.59,"is_bot":true},{"t":71,"event":"BotPosition","px":208,"py":392,"x":-296.41,"z":117.65,"is_bot":true},{"t":71,"event":"BotPosition","px":744,"py":535,"x":226.49,"z":-22.84,"is_bot":true},{"t":71,"event":"BotPosition","px":227,"py":392,"x":-278.3,"z":117.28,"is_bot":true},{"t":71,"event":"BotPosition","px":715,"py":422,"x":198.2,"z":87.6,"is_bot":true},{"t":71,"event":"BotPosition","px":235,"py":603,"x":-270.25,"z":-89.07,"is_bot":true},{"t":71,"event":"BotPosition","px":617,"py":232,"x":102.87,"z":273.14,"is_bot":true},{"t":71,"event":"Position","px":203,"py":619,"x":-302.06,"z":-104.28,"is_bot":false},{"t":71,"event":"Loot","px":203,"py":619,"x":-302.06,"z":-104.28,"is_bot":false},{"t":72,"event":"Loot","px":203,"py":619,"x":-302.06,"z":-104.28,"is_bot":false},{"t":76,"event":"BotPosition","px":590,"py":478,"x":76.4,"z":33.12,"is_bot":true},{"t":76,"event":"BotPosition","px":201,"py":411,"x":-303.33,"z":98.89,"is_bot":true},{"t":76,"event":"BotPosition","px":724,"py":521,"x":206.91,"z":-8.31,"is_bot":true},{"t":76,"event":"BotPosition","px":224,"py":387,"x":-281.35,"z":121.78,"is_bot":true},{"t":76,"event":"BotPosition","px":731,"py":439,"x":213.55,"z":70.94,"is_bot":true},{"t":76,"event":"BotPosition","px":211,"py":610,"x":-293.87,"z":-95.99,"is_bot":true},{"t":76,"event":"BotPosition","px":614,"py":255,"x":99.58,"z":251.1,"is_bot":true},{"t":76,"event":"Position","px":210,"py":624,"x":-294.84,"z":-109.17,"is_bot":false},{"t":81,"event":"BotPosition","px":596,"py":484,"x":81.71,"z":27.76,"is_bot":true},{"t":81,"event":"BotPosition","px":213,"py":426,"x":-292.19,"z":84.37,"is_bot":true},{"t":81,"event":"BotPosition","px":709,"py":506,"x":192.32,"z":5.52,"is_bot":true},{"t":81,"event":"BotPosition","px":244,"py":382,"x":-261.61,"z":126.58,"is_bot":true},{"t":81,"event":"BotPosition","px":753,"py":446,"x":234.88,"z":64.12,"is_bot":true},{"t":81,"event":"BotPosition","px":208,"py":614,"x":-296.94,"z":-99.17,"is_bot":true},{"t":81,"event":"BotPosition","px":594,"py":269,"x":79.72,"z":237.28,"is_bot":true},{"t":81,"event":"Position","px":213,"py":629,"x":-292.16,"z":-113.96,"is_bot":false},{"t":86,"event":"BotPosition","px":607,"py":484,"x":93.2,"z":27.32,"is_bot":true},{"t":86,"event":"BotPosition","px":231,"py":437,"x":-274.73,"z":72.78,"is_bot":true},{"t":86,"event":"BotPosition","px":689,"py":492,"x":172.53,"z":19.94,"is_bot":true},{"t":86,"event":"BotPosition","px":259,"py":362,"x":-247.24,"z":146.21,"is_bot":true},{"t":86,"event":"BotPosition","px":769,"py":439,"x":250.66,"z":70.93,"is_bot":true},{"t":86,"event":"BotPosition","px":218,"py":616,"x":-287.53,"z":-101.97,"is_bot":true},{"t":86,"event":"BotPosition","px":596,"py":252,"x":81.82,"z":253.93,"is_bot":true},{"t":91,"event":"BotPosition","px":623,"py":494,"x":108.26,"z":17.39,"is_bot":true},{"t":91,"event":"BotPosition","px":240,"py":461,"x":-265.92,"z":49.82,"is_bot":true},{"t":91,"event":"BotPosition","px":673,"py":486,"x":156.93,"z":25.59,"is_bot":true},{"t":91,"event":"BotPosition","px":252,"py":382,"x":-253.64,"z":127.29,"is_bot":true},{"t":91,"event":"BotPosition","px":758,"py":445,"x":240.71,"z":65.83,"is_bot":true},{"t":91,"event":"BotPosition","px":200,"py":611,"x":-304.57,"z":-96.66,"is_bot":true},{"t":91,"event":"BotPosition","px":583,"py":231,"x":68.91,"z":274.87,"is_bot":true},{"t":91,"event":"Position","px":211,"py":624,"x":-294.39,"z":-109.68,"is_bot":false},{"t":96,"event":"BotPosition","px":634,"py":511,"x":119.36,"z":1.22,"is_bot":true},{"t":96,"event":"BotPosition","px":247,"py":480,"x":-258.95,"z":31.65,"is_bot":true},{"t":96,"event":"BotPosition","px":681,"py":503,"x":165.14,"z":8.68,"is_bot":true},{"t":96,"event":"BotPosition","px":244,"py":405,"x":-261.89,"z":104.09,"is_bot":true},{"t":96,"event":"BotPosition","px":739,"py":460,"x":221.93,"z":50.52,"is_bot":true},{"t":96,"event":"BotPosition","px":593,"py":219,"x":78.8,"z":286.14,"is_bot":true},{"t":96,"event":"Position","px":211,"py":626,"x":-293.71,"z":-111.24,"is_bot":false},{"t":101,"event":"BotPosition","px":628,"py":503,"x":112.82,"z":8.6,"is_bot":true},{"t":101,"event":"BotPosition","px":236,"py":497,"x":-269.09,"z":14.49,"is_bot":true},{"t":101,"event":"BotPosition","px":675,"py":485,"x":159.09,"z":26.03,"is_bot":true},{"t":101,"event":"BotPosition","px":241,"py":390,"x":-265.0,"z":119.32,"is_bot":true},{"t":101,"event":"BotPosition","px":749,"py":466,"x":231.51,"z":44.77,"is_bot":true},{"t":101,"event":"BotPosition","px":218,"py":624,"x":-286.76,"z":-109.68,"is_bot":true},{"t":101,"event":"BotPosition","px":582,"py":227,"x":68.75,"z":278.07,"is_bot":true},{"t":106,"event":"BotPosition","px":606,"py":495,"x":91.61,"z":16.51,"is_bot":true},{"t":106,"event":"BotPosition","px":238,"py":522,"x":-267.35,"z":-9.85,"is_bot":true},{"t":106,"event":"BotPosition","px":254,"py":370,"x":-251.47,"z":139.02,"is_bot":true},{"t":106,"event":"BotPosition","px":770,"py":476,"x":251.73,"z":35.11,"is_bot":true},{"t":106,"event":"BotPosition","px":223,"py":618,"x":-282.1,"z":-103.38,"is_bot":true},{"t":106,"event":"BotPosition","px":566,"py":232,"x":52.89,"z":273.14,"is_bot":true},{"t":111,"event":"BotPosition","px":605,"py":491,"x":91.17,"z":20.08,"is_bot":true},{"t":111,"event":"BotPosition","px":249,"py":543,"x":-256.61,"z":-30.22,"is_bot":true},{"t":111,"event":"BotPosition","px":675,"py":490,"x":158.72,"z":21.55,"is_bot":true},{"t":111,"event":"BotPosition","px":268,"py":351,"x":-238.33,"z":157.49,"is_bot":true},{"t":111,"event":"BotPosition","px":776,"py":488,"x":257.64,"z":23.67,"is_bot":true},{"t":111,"event":"BotPosition","px":571,"py":232,"x":57.13,"z":273.51,"is_bot":true},{"t":115,"event":"Loot","px":212,"py":625,"x":-293.43,"z":-110.42,"is_bot":false},{"t":116,"event":"BotPosition","px":589,"py":494,"x":74.74,"z":17.41,"is_bot":true},{"t":116,"event":"BotPosition","px":270,"py":557,"x":-236.31,"z":-43.7,"is_bot":true},{"t":116,"event":"BotPosition","px":678,"py":496,"x":161.87,"z":15.65,"is_bot":true},{"t":116,"event":"BotPosition","px":288,"py":340,"x":-218.61,"z":168.12,"is_bot":true},{"t":116,"event":"BotPosition","px":794,"py":491,"x":275.16,"z":20.87,"is_bot":true},{"t":116,"event":"BotPosition","px":214,"py":622,"x":-291.17,"z":-107.6,"is_bot":true},{"t":116,"event":"BotPosition","px":595,"py":237,"x":81.04,"z":268.23,"is_bot":true},{"t":121,"event":"BotPosition","px":571,"py":510,"x":57.81,"z":1.98,"is_bot":true},{"t":121,"event":"BotPosition","px":294,"py":554,"x":-213.1,"z":-41.38,"is_bot":true},{"t":121,"event":"BotPosition","px":672,"py":486,"x":156.56,"z":24.95,"is_bot":true},{"t":121,"event":"BotPosition","px":282,"py":343,"x":-224.42,"z":164.79,"is_bot":true},{"t":121,"event":"BotPosition","px":799,"py":502,"x":280.07,"z":9.95,"is_bot":true},{"t":121,"event":"BotPosition","px":219,"py":625,"x":-286.39,"z":-110.73,"is_bot":true},{"t":121,"event":"BotPosition","px":602,"py":246,"x":87.6,"z":260.07,"is_bot":true},{"t":121,"event":"Position","px":210,"py":624,"x":-294.61,"z":-109.37,"is_bot":false},{"t":126,"event":"BotPosition","px":555,"py":527,"x":42.24,"z":-14.91,"is_bot":true},{"t":126,"event":"BotPosition","px":313,"py":544,"x":-194.69,"z":-31.51,"is_bot":true},{"t":126,"event":"BotPosition","px":673,"py":486,"x":156.77,"z":25.6,"is_bot":true},{"t":126,"event":"BotPosition","px":297,"py":339,"x":-210.44,"z":168.52,"is_bot":true},{"t":126,"event":"BotPosition","px":797,"py":527,"x":278.53,"z":-14.49,"is_bot":true},{"t":126,"event":"BotPosition","px":594,"py":269,"x":79.94,"z":236.85,"is_bot":true},{"t":131,"event":"BotPosition","px":545,"py":544,"x":32.01,"z":-31.33,"is_bot":true},{"t":131,"event":"BotPosition","px":311,"py":540,"x":-195.98,"z":-26.87,"is_bot":true},{"t":131,"event":"BotPosition","px":663,"py":493,"x":147.06,"z":18.8,"is_bot":true},{"t":131,"event":"BotPosition","px":304,"py":341,"x":-203.44,"z":166.84,"is_bot":true},{"t":131,"event":"BotPosition","px":797,"py":531,"x":278.31,"z":-18.32,"is_bot":true},{"t":131,"event":"BotPosition","px":200,"py":619,"x":-304.63,"z":-104.73,"is_bot":true},{"t":131,"event":"BotPosition","px":587,"py":287,"x":73.54,"z":219.27,"is_bot":true},{"t":136,"event":"BotPosition","px":546,"py":553,"x":33.15,"z":-40.39,"is_bot":true},{"t":136,"event":"BotPosition","px":327,"py":549,"x":-180.72,"z":-35.83,"is_bot":true},{"t":136,"event":"BotPosition","px":282,"py":353,"x":-224.67,"z":155.32,"is_bot":true},{"t":136,"event":"BotPosition","px":798,"py":508,"x":279.39,"z":3.88,"is_bot":true},{"t":136,"event":"BotPosition","px":210,"py":616,"x":-294.79,"z":-101.12,"is_bot":true},{"t":136,"event":"BotPosition","px":602,"py":302,"x":87.45,"z":205.42,"is_bot":true},{"t":141,"event":"BotPosition","px":562,"py":567,"x":49.1,"z":-53.99,"is_bot":true},{"t":141,"event":"BotPosition","px":315,"py":532,"x":-192.51,"z":-19.58,"is_bot":true},{"t":141,"event":"BotPosition","px":655,"py":496,"x":139.48,"z":15.9,"is_bot":true},{"t":141,"event":"BotPosition","px":263,"py":366,"x":-243.37,"z":142.38,"is_bot":true},{"t":141,"event":"BotPosition","px":799,"py":498,"x":279.88,"z":14.03,"is_bot":true},{"t":141,"event":"BotPosition","px":201,"py":621,"x":-303.42,"z":-106.56,"is_bot":true},{"t":141,"event":"BotPosition","px":609,"py":311,"x":95.08,"z":196.2,"is_bot":true},{"t":146,"event":"BotPosition","px":578,"py":564,"x":64.42,"z":-50.98,"is_bot":true},{"t":146,"event":"BotPosition","px":309,"py":538,"x":-198.44,"z":-25.39,"is_bot":true},{"t":146,"event":"BotPosition","px":647,"py":499,"x":131.49,"z":12.54,"is_bot":true},{"t":146,"event":"BotPosition","px":244,"py":383,"x":-261.41,"z":125.93,"is_bot":true},{"t":146,"event":"BotPosition","px":797,"py":523,"x":278.72,"z":-10.47,"is_bot":true},{"t":146,"event":"BotPosition","px":201,"py":617,"x":-303.34,"z":-102.63,"is_bot":true},{"t":146,"event":"BotPosition","px":591,"py":298,"x":76.67,"z":208.72,"is_bot":true},{"t":146,"event":"Position","px":211,"py":625,"x":-293.5,"z":-110.77,"is_bot":false},{"t":151,"event":"BotPosition","px":565,"py":569,"x":51.88,"z":-55.61,"is_bot":true},{"t":151,"event":"BotPosition","px":650,"py":481,"x":134.87,"z":30.59,"is_bot":true},{"t":151,"event":"BotPosition","px":223,"py":385,"x":-282.22,"z":123.7,"is_bot":true},{"t":151,"event":"BotPosition","px":804,"py":537,"x":285.22,"z":-24.24,"is_bot":true},{"t":151,"event":"BotPosition","px":201,"py":621,"x":-304.16,"z":-106.45,"is_bot":true},{"t":151,"event":"BotPosition","px":586,"py":279,"x":72.01,"z":227.06,"is_bot":true},{"t":156,"event":"BotPosition","px":586,"py":568,"x":71.94,"z":-54.41,"is_bot":true},{"t":156,"event":"BotPosition","px":659,"py":479,"x":143.58,"z":32.51,"is_bot":true},{"t":156,"event":"BotPosition","px":206,"py":388,"x":-298.59,"z":120.78,"is_bot":true},{"t":156,"event":"BotPosition","px":802,"py":562,"x":283.01,"z":-48.77,"is_bot":true},{"t":156,"event":"BotPosition","px":201,"py":617,"x":-303.76,"z":-102.87,"is_bot":true},{"t":156,"event":"BotPosition","px":571,"py":259,"x":58.07,"z":247.32,"is_bot":true},{"t":161,"event":"BotPosition","px":609,"py":574,"x":94.57,"z":-60.68,"is_bot":true},{"t":161,"event":"BotPosition","px":648,"py":486,"x":132.83,"z":25.83,"is_bot":true},{"t":161,"event":"BotPosition","px":204,"py":388,"x":-300.73,"z":121.41,"is_bot":true},{"t":161,"event":"BotPosition","px":795,"py":581,"x":276.38,"z":-67.31,"is_bot":true},{"t":161,"event":"BotPosition","px":205,"py":611,"x":-299.62,"z":-97.16,"is_bot":true},{"t":161,"event":"BotPosition","px":557,"py":259,"x":44.18,"z":247.14,"is_bot":true},{"t":166,"event":"BotPosition","px":628,"py":577,"x":113.44,"z":-63.61,"is_bot":true},{"t":166,"event":"BotPosition","px":645,"py":502,"x":130.32,"z":9.42,"is_bot":true},{"t":166,"event":"BotPosition","px":220,"py":394,"x":-284.75,"z":115.42,"is_bot":true},{"t":166,"event":"BotPosition","px":775,"py":578,"x":256.85,"z":-64.33,"is_bot":true},{"t":166,"event":"BotPosition","px":206,"py":623,"x":-299.02,"z":-108.22,"is_bot":true},{"t":166,"event":"BotPosition","px":557,"py":253,"x":43.6,"z":252.51,"is_bot":true},{"t":171,"event":"BotPosition","px":643,"py":580,"x":127.91,"z":-66.44,"is_bot":true},{"t":171,"event":"BotKilled","px":646,"py":502,"x":130.73,"z":10.02,"is_bot":true},{"t":171,"event":"BotPosition","px":215,"py":413,"x":-289.68,"z":96.41,"is_bot":true},{"t":171,"event":"BotPosition","px":750,"py":577,"x":232.45,"z":-63.84,"is_bot":true},{"t":171,"event":"BotPosition","px":201,"py":620,"x":-303.32,"z":-105.96,"is_bot":true},{"t":176,"event":"BotPosition","px":642,"py":571,"x":126.69,"z":-57.52,"is_bot":true},{"t":176,"event":"BotPosition","px":753,"py":583,"x":235.74,"z":-69.3,"is_bot":true},{"t":176,"event":"BotPosition","px":200,"py":619,"x":-304.61,"z":-104.89,"is_bot":true},{"t":176,"event":"BotPosition","px":569,"py":249,"x":56.1,"z":256.64,"is_bot":true},{"t":181,"event":"BotPosition","px":642,"py":568,"x":126.57,"z":-54.98,"is_bot":true},{"t":181,"event":"BotPosition","px":230,"py":395,"x":-275.36,"z":113.77,"is_bot":true},{"t":181,"event":"BotPosition","px":776,"py":590,"x":257.62,"z":-75.81,"is_bot":true},{"t":181,"event":"BotPosition","px":591,"py":242,"x":76.73,"z":263.47,"is_bot":true},{"t":186,"event":"BotPosition","px":224,"py":405,"x":-281.3,"z":104.68,"is_bot":true},{"t":186,"event":"BotPosition","px":756,"py":587,"x":238.42,"z":-73.15,"is_bot":true},{"t":186,"event":"BotPosition","px":580,"py":221,"x":66.46,"z":284.08,"is_bot":true},{"t":192,"event":"BotPosition","px":225,"py":427,"x":-280.3,"z":82.63,"is_bot":true},{"t":192,"event":"BotPosition","px":732,"py":582,"x":214.41,"z":-68.57,"is_bot":true},{"t":192,"event":"BotPosition","px":199,"py":618,"x":-305.63,"z":-103.97,"is_bot":true},{"t":192,"event":"BotPosition","px":584,"py":216,"x":70.38,"z":288.66,"is_bot":true},{"t":197,"event":"BotPosition","px":227,"py":402,"x":-278.5,"z":107.18,"is_bot":true},{"t":197,"event":"BotPosition","px":711,"py":579,"x":193.88,"z":-65.91,"is_bot":true},{"t":197,"event":"BotPosition","px":201,"py":617,"x":-303.57,"z":-102.45,"is_bot":true},{"t":197,"event":"BotPosition","px":586,"py":209,"x":72.07,"z":295.8,"is_bot":true},{"t":202,"event":"BotPosition","px":305,"py":548,"x":-201.72,"z":-35.49,"is_bot":true},{"t":202,"event":"BotPosition","px":222,"py":384,"x":-283.1,"z":124.93,"is_bot":true},{"t":202,"event":"BotPosition","px":686,"py":576,"x":169.61,"z":-62.84,"is_bot":true},{"t":202,"event":"BotPosition","px":588,"py":205,"x":74.46,"z":300.17,"is_bot":true},{"t":207,"event":"BotPosition","px":302,"py":550,"x":-205.13,"z":-36.85,"is_bot":true},{"t":207,"event":"BotPosition","px":227,"py":402,"x":-278.42,"z":107.04,"is_bot":true},{"t":207,"event":"BotPosition","px":663,"py":581,"x":147.45,"z":-67.06,"is_bot":true},{"t":207,"event":"BotPosition","px":210,"py":612,"x":-294.48,"z":-97.86,"is_bot":true},{"t":207,"event":"BotPosition","px":593,"py":210,"x":79.3,"z":294.94,"is_bot":true},{"t":212,"event":"BotPosition","px":310,"py":539,"x":-197.41,"z":-25.96,"is_bot":true},{"t":212,"event":"BotPosition","px":227,"py":428,"x":-278.77,"z":82.37,"is_bot":true},{"t":212,"event":"BotPosition","px":650,"py":580,"x":134.74,"z":-66.19,"is_bot":true},{"t":212,"event":"BotPosition","px":203,"py":621,"x":-302.18,"z":-106.11,"is_bot":true},{"t":212,"event":"BotPosition","px":598,"py":216,"x":84.31,"z":289.29,"is_bot":true},{"t":217,"event":"BotPosition","px":643,"py":571,"x":128.32,"z":-57.27,"is_bot":true},{"t":217,"event":"BotPosition","px":315,"py":525,"x":-192.3,"z":-12.51,"is_bot":true},{"t":217,"event":"BotPosition","px":221,"py":440,"x":-283.85,"z":69.88,"is_bot":true},{"t":217,"event":"BotPosition","px":642,"py":584,"x":126.85,"z":-70.77,"is_bot":true},{"t":217,"event":"BotPosition","px":207,"py":620,"x":-298.28,"z":-105.74,"is_bot":true},{"t":217,"event":"BotPosition","px":593,"py":217,"x":78.7,"z":287.95,"is_bot":true},{"t":222,"event":"BotPosition","px":644,"py":583,"x":129.31,"z":-69.24,"is_bot":true},{"t":222,"event":"BotPosition","px":319,"py":521,"x":-188.61,"z":-9.01,"is_bot":true},{"t":222,"event":"BotPosition","px":219,"py":422,"x":-286.05,"z":88.05,"is_bot":true},{"t":222,"event":"BotPosition","px":631,"py":589,"x":116.62,"z":-75.12,"is_bot":true},{"t":222,"event":"BotPosition","px":202,"py":616,"x":-302.92,"z":-101.66,"is_bot":true},{"t":222,"event":"BotPosition","px":585,"py":218,"x":71.18,"z":287.24,"is_bot":true},{"t":227,"event":"BotPosition","px":629,"py":589,"x":113.84,"z":-74.86,"is_bot":true},{"t":227,"event":"BotPosition","px":316,"py":541,"x":-190.92,"z":-28.59,"is_bot":true},{"t":227,"event":"BotPosition","px":222,"py":437,"x":-283.3,"z":73.13,"is_bot":true},{"t":227,"event":"BotPosition","px":622,"py":585,"x":107.69,"z":-71.32,"is_bot":true},{"t":227,"event":"BotPosition","px":199,"py":619,"x":-305.27,"z":-104.34,"is_bot":true},{"t":227,"event":"BotPosition","px":578,"py":218,"x":64.74,"z":287.08,"is_bot":true},{"t":232,"event":"BotPosition","px":620,"py":584,"x":105.06,"z":-69.86,"is_bot":true},{"t":232,"event":"BotPosition","px":227,"py":459,"x":-278.24,"z":52.18,"is_bot":true},{"t":232,"event":"BotPosition","px":613,"py":591,"x":98.91,"z":-77.46,"is_bot":true},{"t":232,"event":"BotPosition","px":200,"py":619,"x":-304.65,"z":-104.31,"is_bot":true},{"t":232,"event":"BotPosition","px":571,"py":218,"x":57.24,"z":287.09,"is_bot":true},{"t":237,"event":"BotPosition","px":615,"py":589,"x":100.93,"z":-75.35,"is_bot":true},{"t":237,"event":"BotPosition","px":308,"py":540,"x":-199.08,"z":-27.41,"is_bot":true},{"t":237,"event":"BotPosition","px":226,"py":453,"x":-279.45,"z":57.49,"is_bot":true},{"t":237,"event":"BotPosition","px":614,"py":583,"x":99.82,"z":-69.57,"is_bot":true},{"t":237,"event":"BotPosition","px":564,"py":215,"x":50.88,"z":289.72,"is_bot":true},{"t":242,"event":"BotPosition","px":617,"py":587,"x":102.79,"z":-73.55,"is_bot":true},{"t":242,"event":"BotPosition","px":327,"py":549,"x":-180.92,"z":-36.26,"is_bot":true},{"t":242,"event":"BotPosition","px":231,"py":432,"x":-274.47,"z":77.95,"is_bot":true},{"t":242,"event":"BotPosition","px":616,"py":588,"x":101.72,"z":-74.44,"is_bot":true},{"t":242,"event":"BotPosition","px":558,"py":210,"x":45.21,"z":294.71,"is_bot":true},{"t":247,"event":"BotPosition","px":615,"py":589,"x":100.94,"z":-75.23,"is_bot":true},{"t":247,"event":"BotPosition","px":349,"py":562,"x":-159.52,"z":-48.52,"is_bot":true},{"t":247,"event":"BotPosition","px":227,"py":435,"x":-277.87,"z":75.51,"is_bot":true},{"t":247,"event":"BotPosition","px":617,"py":589,"x":102.28,"z":-75.31,"is_bot":true},{"t":247,"event":"BotPosition","px":212,"py":621,"x":-292.72,"z":-106.03,"is_bot":true},{"t":247,"event":"BotPosition","px":560,"py":207,"x":47.12,"z":297.55,"is_bot":true},{"t":252,"event":"BotPosition","px":614,"py":591,"x":99.76,"z":-77.15,"is_bot":true},{"t":252,"event":"BotPosition","px":354,"py":564,"x":-154.13,"z":-50.38,"is_bot":true},{"t":252,"event":"BotPosition","px":204,"py":438,"x":-300.64,"z":72.05,"is_bot":true},{"t":252,"event":"BotPosition","px":608,"py":598,"x":93.34,"z":-83.58,"is_bot":true},{"t":252,"event":"BotPosition","px":219,"py":625,"x":-286.07,"z":-109.9,"is_bot":true},{"t":252,"event":"BotPosition","px":568,"py":206,"x":54.52,"z":299.05,"is_bot":true},{"t":257,"event":"BotPosition","px":606,"py":599,"x":92.09,"z":-85.22,"is_bot":true},{"t":257,"event":"BotPosition","px":357,"py":561,"x":-151.36,"z":-48.3,"is_bot":true},{"t":257,"event":"BotPosition","px":201,"py":430,"x":-303.98,"z":80.38,"is_bot":true},{"t":257,"event":"BotPosition","px":604,"py":611,"x":90.04,"z":-96.34,"is_bot":true},{"t":257,"event":"BotPosition","px":212,"py":621,"x":-292.61,"z":-106.02,"is_bot":true},{"t":257,"event":"BotPosition","px":569,"py":206,"x":55.91,"z":298.91,"is_bot":true},{"t":262,"event":"BotPosition","px":606,"py":612,"x":92.28,"z":-97.57,"is_bot":true},{"t":262,"event":"BotPosition","px":368,"py":568,"x":-140.9,"z":-54.71,"is_bot":true},{"t":262,"event":"BotPosition","px":212,"py":413,"x":-292.64,"z":96.36,"is_bot":true},{"t":262,"event":"BotPosition","px":605,"py":605,"x":91.25,"z":-91.03,"is_bot":true},{"t":262,"event":"BotPosition","px":214,"py":637,"x":-290.89,"z":-121.84,"is_bot":true},{"t":262,"event":"BotPosition","px":563,"py":210,"x":50.29,"z":294.63,"is_bot":true},{"t":265,"event":"BotKilled","px":607,"py":608,"x":92.69,"z":-93.76,"is_bot":true},{"t":265,"event":"BotKill","px":607,"py":601,"x":92.58,"z":-87.28,"is_bot":true},{"t":267,"event":"BotPosition","px":390,"py":579,"x":-119.11,"z":-65.65,"is_bot":true},{"t":267,"event":"BotPosition","px":226,"py":404,"x":-279.43,"z":105.88,"is_bot":true},{"t":267,"event":"BotPosition","px":605,"py":602,"x":90.69,"z":-88.17,"is_bot":true},{"t":267,"event":"BotPosition","px":211,"py":620,"x":-293.9,"z":-105.85,"is_bot":true},{"t":267,"event":"BotPosition","px":559,"py":217,"x":46.37,"z":288.53,"is_bot":true},{"t":272,"event":"BotPosition","px":411,"py":590,"x":-98.31,"z":-76.45,"is_bot":true},{"t":272,"event":"BotPosition","px":233,"py":415,"x":-272.52,"z":94.55,"is_bot":true},{"t":272,"event":"BotPosition","px":602,"py":613,"x":88.07,"z":-98.44,"is_bot":true},{"t":272,"event":"BotPosition","px":219,"py":625,"x":-285.65,"z":-110.05,"is_bot":true},{"t":272,"event":"BotPosition","px":555,"py":223,"x":42.28,"z":282.19,"is_bot":true},{"t":277,"event":"BotPosition","px":432,"py":604,"x":-78.42,"z":-89.51,"is_bot":true},{"t":277,"event":"BotPosition","px":251,"py":427,"x":-255.22,"z":82.81,"is_bot":true},{"t":277,"event":"BotPosition","px":608,"py":598,"x":93.35,"z":-83.92,"is_bot":true},{"t":277,"event":"BotPosition","px":553,"py":230,"x":39.92,"z":275.61,"is_bot":true},{"t":282,"event":"BotPosition","px":437,"py":612,"x":-73.53,"z":-97.66,"is_bot":true},{"t":282,"event":"BotPosition","px":259,"py":448,"x":-247.54,"z":62.69,"is_bot":true},{"t":282,"event":"BotPosition","px":621,"py":577,"x":106.91,"z":-63.74,"is_bot":true},{"t":282,"event":"BotPosition","px":209,"py":621,"x":-295.71,"z":-106.67,"is_bot":true},{"t":282,"event":"BotPosition","px":554,"py":237,"x":41.11,"z":268.15,"is_bot":true},{"t":287,"event":"BotPosition","px":261,"py":451,"x":-245.5,"z":59.25,"is_bot":true},{"t":287,"event":"BotPosition","px":628,"py":571,"x":113.61,"z":-57.86,"is_bot":true},{"t":287,"event":"BotPosition","px":225,"py":631,"x":-280.19,"z":-116.18,"is_bot":true},{"t":287,"event":"BotPosition","px":555,"py":245,"x":42.26,"z":260.99,"is_bot":true},{"t":292,"event":"BotPosition","px":249,"py":438,"x":-257.06,"z":72.41,"is_bot":true},{"t":292,"event":"BotPosition","px":610,"py":572,"x":95.93,"z":-58.89,"is_bot":true},{"t":292,"event":"BotPosition","px":219,"py":635,"x":-286.54,"z":-120.33,"is_bot":true},{"t":292,"event":"BotPosition","px":551,"py":260,"x":37.71,"z":245.91,"is_bot":true},{"t":297,"event":"BotPosition","px":427,"py":603,"x":-83.21,"z":-88.94,"is_bot":true},{"t":297,"event":"BotPosition","px":227,"py":436,"x":-278.62,"z":74.43,"is_bot":true},{"t":297,"event":"BotPosition","px":592,"py":578,"x":77.98,"z":-64.38,"is_bot":true},{"t":297,"event":"BotPosition","px":195,"py":631,"x":-309.46,"z":-115.74,"is_bot":true},{"t":297,"event":"BotPosition","px":545,"py":272,"x":31.93,"z":234.49,"is_bot":true},{"t":302,"event":"BotPosition","px":422,"py":580,"x":-87.78,"z":-66.8,"is_bot":true},{"t":302,"event":"BotPosition","px":224,"py":437,"x":-281.23,"z":73.44,"is_bot":true},{"t":302,"event":"BotPosition","px":581,"py":579,"x":67.3,"z":-65.62,"is_bot":true},{"t":302,"event":"BotPosition","px":199,"py":612,"x":-305.59,"z":-97.71,"is_bot":true},{"t":302,"event":"BotPosition","px":546,"py":267,"x":32.93,"z":238.9,"is_bot":true},{"t":307,"event":"BotPosition","px":425,"py":577,"x":-85.43,"z":-63.1,"is_bot":true},{"t":307,"event":"BotPosition","px":568,"py":573,"x":54.26,"z":-59.58,"is_bot":true},{"t":307,"event":"BotPosition","px":222,"py":617,"x":-282.84,"z":-103.0,"is_bot":true},{"t":312,"event":"BotPosition","px":205,"py":439,"x":-299.76,"z":71.74,"is_bot":true},{"t":312,"event":"BotPosition","px":558,"py":584,"x":45.27,"z":-69.93,"is_bot":true},{"t":312,"event":"BotPosition","px":243,"py":630,"x":-262.9,"z":-114.81,"is_bot":true},{"t":317,"event":"BotPosition","px":191,"py":437,"x":-313.28,"z":72.99,"is_bot":true},{"t":317,"event":"BotPosition","px":543,"py":584,"x":30.56,"z":-70.42,"is_bot":true},{"t":317,"event":"BotPosition","px":252,"py":625,"x":-254.26,"z":-110.37,"is_bot":true},{"t":317,"event":"BotPosition","px":540,"py":273,"x":27.06,"z":233.11,"is_bot":true},{"t":322,"event":"BotPosition","px":520,"py":586,"x":7.34,"z":-72.4,"is_bot":true},{"t":322,"event":"BotPosition","px":242,"py":602,"x":-263.96,"z":-87.92,"is_bot":true},{"t":322,"event":"BotPosition","px":529,"py":280,"x":16.7,"z":226.42,"is_bot":true},{"t":325,"event":"BotKilled","px":532,"py":279,"x":19.95,"z":227.42,"is_bot":true},{"t":327,"event":"BotPosition","px":437,"py":590,"x":-73.39,"z":-76.56,"is_bot":true},{"t":327,"event":"BotPosition","px":201,"py":439,"x":-303.31,"z":71.2,"is_bot":true},{"t":327,"event":"BotPosition","px":510,"py":586,"x":-1.71,"z":-72.71,"is_bot":true},{"t":327,"event":"BotPosition","px":257,"py":616,"x":-248.95,"z":-102.0,"is_bot":true},{"t":332,"event":"BotPosition","px":213,"py":441,"x":-291.92,"z":69.76,"is_bot":true},{"t":332,"event":"BotPosition","px":271,"py":629,"x":-235.43,"z":-114.61,"is_bot":true},{"t":337,"event":"BotPosition","px":427,"py":582,"x":-82.97,"z":-68.14,"is_bot":true},{"t":337,"event":"BotPosition","px":214,"py":435,"x":-290.9,"z":74.71,"is_bot":true},{"t":337,"event":"BotPosition","px":284,"py":631,"x":-222.5,"z":-116.18,"is_bot":true},{"t":342,"event":"BotPosition","px":425,"py":576,"x":-84.79,"z":-62.46,"is_bot":true},{"t":342,"event":"BotPosition","px":221,"py":427,"x":-283.72,"z":83.03,"is_bot":true},{"t":342,"event":"BotPosition","px":295,"py":629,"x":-212.04,"z":-114.46,"is_bot":true},{"t":347,"event":"BotPosition","px":436,"py":597,"x":-73.92,"z":-83.22,"is_bot":true},{"t":347,"event":"BotPosition","px":233,"py":408,"x":-272.06,"z":101.45,"is_bot":true},{"t":347,"event":"BotPosition","px":275,"py":614,"x":-231.3,"z":-99.25,"is_bot":true},{"t":352,"event":"BotPosition","px":437,"py":612,"x":-73.47,"z":-97.58,"is_bot":true},{"t":352,"event":"BotPosition","px":249,"py":389,"x":-256.54,"z":120.46,"is_bot":true},{"t":352,"event":"BotPosition","px":264,"py":604,"x":-242.66,"z":-90.27,"is_bot":true},{"t":357,"event":"BotPosition","px":434,"py":613,"x":-76.54,"z":-98.48,"is_bot":true},{"t":357,"event":"BotPosition","px":268,"py":373,"x":-238.68,"z":135.84,"is_bot":true},{"t":357,"event":"BotPosition","px":269,"py":609,"x":-237.04,"z":-94.36,"is_bot":true},{"t":362,"event":"BotPosition","px":433,"py":607,"x":-77.37,"z":-92.69,"is_bot":true},{"t":362,"event":"BotPosition","px":280,"py":394,"x":-226.92,"z":115.08,"is_bot":true},{"t":362,"event":"BotPosition","px":506,"py":586,"x":-6.21,"z":-72.59,"is_bot":true},{"t":362,"event":"BotPosition","px":282,"py":615,"x":-224.39,"z":-100.72,"is_bot":true},{"t":367,"event":"BotPosition","px":440,"py":624,"x":-70.42,"z":-109.05,"is_bot":true},{"t":367,"event":"BotPosition","px":291,"py":416,"x":-216.1,"z":93.36,"is_bot":true},{"t":367,"event":"BotPosition","px":300,"py":631,"x":-207.23,"z":-116.59,"is_bot":true},{"t":373,"event":"BotPosition","px":441,"py":630,"x":-69.23,"z":-115.54,"is_bot":true},{"t":373,"event":"BotPosition","px":303,"py":438,"x":-203.71,"z":72.52,"is_bot":true},{"t":373,"event":"BotPosition","px":501,"py":586,"x":-10.96,"z":-72.47,"is_bot":true},{"t":373,"event":"BotPosition","px":316,"py":628,"x":-191.01,"z":-112.96,"is_bot":true},{"t":378,"event":"BotPosition","px":441,"py":636,"x":-69.38,"z":-120.95,"is_bot":true},{"t":378,"event":"BotPosition","px":303,"py":463,"x":-204.17,"z":48.01,"is_bot":true},{"t":378,"event":"BotPosition","px":483,"py":582,"x":-28.79,"z":-68.58,"is_bot":true},{"t":378,"event":"BotPosition","px":316,"py":623,"x":-191.5,"z":-108.16,"is_bot":true},{"t":383,"event":"BotPosition","px":444,"py":644,"x":-66.27,"z":-128.9,"is_bot":true},{"t":383,"event":"BotPosition","px":302,"py":488,"x":-204.64,"z":23.4,"is_bot":true},{"t":383,"event":"BotPosition","px":460,"py":573,"x":-51.13,"z":-59.54,"is_bot":true},{"t":388,"event":"BotPosition","px":448,"py":628,"x":-62.93,"z":-113.06,"is_bot":true},{"t":388,"event":"BotPosition","px":305,"py":477,"x":-202.52,"z":34.48,"is_bot":true},{"t":388,"event":"BotPosition","px":436,"py":577,"x":-74.68,"z":-63.37,"is_bot":true},{"t":393,"event":"BotPosition","px":442,"py":616,"x":-68.76,"z":-101.81,"is_bot":true},{"t":393,"event":"BotPosition","px":295,"py":480,"x":-212.31,"z":31.39,"is_bot":true},{"t":393,"event":"BotPosition","px":413,"py":584,"x":-96.81,"z":-70.15,"is_bot":true},{"t":393,"event":"Position","px":207,"py":627,"x":-297.43,"z":-112.05,"is_bot":false},{"t":398,"event":"BotPosition","px":437,"py":612,"x":-73.24,"z":-97.34,"is_bot":true},{"t":398,"event":"BotPosition","px":298,"py":490,"x":-209.13,"z":21.89,"is_bot":true},{"t":398,"event":"BotPosition","px":396,"py":597,"x":-113.47,"z":-83.04,"is_bot":true},{"t":398,"event":"Position","px":211,"py":627,"x":-294.02,"z":-112.53,"is_bot":false},{"t":400,"event":"Loot","px":214,"py":631,"x":-290.59,"z":-115.92,"is_bot":false},{"t":403,"event":"BotPosition","px":305,"py":512,"x":-202.57,"z":-0.04,"is_bot":true},{"t":403,"event":"BotPosition","px":380,"py":606,"x":-129.37,"z":-91.51,"is_bot":true},{"t":403,"event":"Position","px":213,"py":631,"x":-291.54,"z":-116.36,"is_bot":false},{"t":404,"event":"Loot","px":213,"py":631,"x":-291.54,"z":-116.36,"is_bot":false},{"t":408,"event":"BotPosition","px":312,"py":536,"x":-195.46,"z":-23.63,"is_bot":true},{"t":408,"event":"BotPosition","px":362,"py":609,"x":-146.17,"z":-94.75,"is_bot":true},{"t":408,"event":"Position","px":210,"py":626,"x":-295.34,"z":-111.52,"is_bot":false},{"t":413,"event":"BotPosition","px":332,"py":548,"x":-176.27,"z":-34.71,"is_bot":true},{"t":413,"event":"BotPosition","px":348,"py":590,"x":-160.07,"z":-75.96,"is_bot":true},{"t":413,"event":"Position","px":213,"py":621,"x":-291.93,"z":-106.37,"is_bot":false},{"t":418,"event":"BotPosition","px":328,"py":551,"x":-179.98,"z":-38.32,"is_bot":true},{"t":418,"event":"BotPosition","px":340,"py":605,"x":-167.89,"z":-90.36,"is_bot":true},{"t":418,"event":"Position","px":220,"py":634,"x":-285.53,"z":-118.86,"is_bot":false},{"t":423,"event":"BotPosition","px":313,"py":568,"x":-194.09,"z":-54.42,"is_bot":true},{"t":423,"event":"Position","px":205,"py":634,"x":-300.19,"z":-119.57,"is_bot":false},{"t":428,"event":"BotPosition","px":298,"py":585,"x":-209.13,"z":-71.65,"is_bot":true},{"t":428,"event":"BotKilled","px":339,"py":609,"x":-169.3,"z":-94.82,"is_bot":true},{"t":428,"event":"Position","px":191,"py":625,"x":-313.69,"z":-110.37,"is_bot":false},{"t":433,"event":"BotPosition","px":282,"py":581,"x":-224.84,"z":-66.89,"is_bot":true},{"t":433,"event":"Position","px":198,"py":610,"x":-306.35,"z":-95.95,"is_bot":false},{"t":438,"event":"BotPosition","px":268,"py":578,"x":-237.81,"z":-64.35,"is_bot":true},{"t":438,"event":"Position","px":213,"py":602,"x":-291.64,"z":-87.79,"is_bot":false},{"t":443,"event":"Position","px":228,"py":608,"x":-277.5,"z":-93.54,"is_bot":false},{"t":448,"event":"Position","px":221,"py":624,"x":-284.14,"z":-109.12,"is_bot":false},{"t":453,"event":"Position","px":208,"py":622,"x":-297.3,"z":-107.04,"is_bot":false},{"t":458,"event":"Position","px":215,"py":622,"x":-289.86,"z":-107.02,"is_bot":false},{"t":463,"event":"Position","px":218,"py":637,"x":-287.48,"z":-121.82,"is_bot":false},{"t":468,"event":"BotPosition","px":283,"py":581,"x":-223.29,"z":-67.33,"is_bot":true},{"t":468,"event":"Position","px":196,"py":633,"x":-308.25,"z":-118.6,"is_bot":false},{"t":473,"event":"BotPosition","px":301,"py":593,"x":-205.93,"z":-79.27,"is_bot":true},{"t":473,"event":"Position","px":181,"py":619,"x":-323.58,"z":-104.23,"is_bot":false},{"t":478,"event":"BotPosition","px":314,"py":608,"x":-193.76,"z":-93.58,"is_bot":true},{"t":478,"event":"Position","px":181,"py":622,"x":-323.51,"z":-107.61,"is_bot":false},{"t":483,"event":"BotPosition","px":319,"py":608,"x":-188.19,"z":-93.4,"is_bot":true},{"t":483,"event":"Position","px":181,"py":627,"x":-323.19,"z":-112.56,"is_bot":false},{"t":488,"event":"BotPosition","px":316,"py":630,"x":-191.36,"z":-115.63,"is_bot":true},{"t":488,"event":"Position","px":202,"py":651,"x":-303.1,"z":-136.07,"is_bot":false},{"t":493,"event":"BotPosition","px":304,"py":632,"x":-203.45,"z":-117.64,"is_bot":true},{"t":493,"event":"Position","px":225,"py":655,"x":-280.03,"z":-140.03,"is_bot":false},{"t":498,"event":"BotPosition","px":438,"py":631,"x":-72.65,"z":-116.12,"is_bot":true},{"t":498,"event":"BotPosition","px":305,"py":613,"x":-202.06,"z":-98.47,"is_bot":true},{"t":498,"event":"Position","px":251,"py":637,"x":-254.49,"z":-122.48,"is_bot":false},{"t":503,"event":"BotPosition","px":433,"py":653,"x":-77.52,"z":-138.0,"is_bot":true},{"t":503,"event":"BotPosition","px":298,"py":592,"x":-208.98,"z":-77.66,"is_bot":true},{"t":503,"event":"Position","px":268,"py":624,"x":-237.89,"z":-109.2,"is_bot":false},{"t":508,"event":"BotPosition","px":414,"py":653,"x":-96.0,"z":-137.92,"is_bot":true},{"t":508,"event":"BotPosition","px":278,"py":580,"x":-228.48,"z":-65.99,"is_bot":true},{"t":508,"event":"Position","px":278,"py":614,"x":-228.89,"z":-99.15,"is_bot":false},{"t":513,"event":"BotPosition","px":269,"py":577,"x":-237.35,"z":-63.0,"is_bot":true},{"t":513,"event":"Position","px":276,"py":612,"x":-230.02,"z":-97.3,"is_bot":false},{"t":523,"event":"Position","px":285,"py":608,"x":-221.7,"z":-93.44,"is_bot":false},{"t":528,"event":"BotPosition","px":437,"py":654,"x":-73.3,"z":-139.05,"is_bot":true},{"t":528,"event":"Position","px":311,"py":591,"x":-195.93,"z":-76.79,"is_bot":false},{"t":529,"event":"BotKilled","px":438,"py":654,"x":-72.19,"z":-139.11,"is_bot":true},{"t":533,"event":"Position","px":326,"py":566,"x":-181.43,"z":-53.1,"is_bot":false},{"t":538,"event":"Position","px":348,"py":560,"x":-159.76,"z":-47.21,"is_bot":false},{"t":544,"event":"Position","px":378,"py":554,"x":-130.82,"z":-41.5,"is_bot":false},{"t":549,"event":"Position","px":404,"py":548,"x":-105.18,"z":-35.12,"is_bot":false},{"t":554,"event":"Position","px":422,"py":539,"x":-87.82,"z":-26.69,"is_bot":false},{"t":584,"event":"Position","px":429,"py":539,"x":-80.57,"z":-26.34,"is_bot":false},{"t":589,"event":"Position","px":443,"py":536,"x":-67.78,"z":-23.23,"is_bot":false},{"t":594,"event":"Position","px":449,"py":516,"x":-61.26,"z":-3.88,"is_bot":false},{"t":599,"event":"Position","px":452,"py":504,"x":-58.88,"z":7.68,"is_bot":false},{"t":604,"event":"Position","px":433,"py":519,"x":-77.21,"z":-6.49,"is_bot":false},{"t":609,"event":"Position","px":410,"py":533,"x":-99.18,"z":-20.94,"is_bot":false},{"t":614,"event":"Position","px":391,"py":552,"x":-117.69,"z":-38.64,"is_bot":false},{"t":619,"event":"Position","px":384,"py":561,"x":-125.25,"z":-48.11,"is_bot":false},{"t":624,"event":"Position","px":369,"py":568,"x":-140.06,"z":-55.16,"is_bot":false},{"t":629,"event":"Position","px":345,"py":559,"x":-163.21,"z":-46.24,"is_bot":false},{"t":634,"event":"Position","px":319,"py":560,"x":-188.47,"z":-46.47,"is_bot":false},{"t":639,"event":"Position","px":292,"py":567,"x":-214.78,"z":-54.1,"is_bot":false},{"t":644,"event":"BotPosition","px":276,"py":580,"x":-230.27,"z":-66.19,"is_bot":true},{"t":644,"event":"Position","px":274,"py":583,"x":-232.24,"z":-69.19,"is_bot":false},{"t":649,"event":"BotPosition","px":270,"py":584,"x":-236.76,"z":-70.53,"is_bot":true},{"t":649,"event":"Position","px":260,"py":587,"x":-246.3,"z":-73.16,"is_bot":false},{"t":654,"event":"BotPosition","px":257,"py":588,"x":-249.07,"z":-73.93,"is_bot":true},{"t":654,"event":"Position","px":237,"py":600,"x":-268.58,"z":-85.67,"is_bot":false},{"t":659,"event":"BotPosition","px":262,"py":590,"x":-244.6,"z":-75.8,"is_bot":true},{"t":659,"event":"Position","px":233,"py":624,"x":-272.65,"z":-109.34,"is_bot":false},{"t":664,"event":"BotPosition","px":269,"py":577,"x":-237.36,"z":-63.01,"is_bot":true},{"t":664,"event":"Position","px":223,"py":646,"x":-281.77,"z":-130.4,"is_bot":false},{"t":669,"event":"Position","px":227,"py":660,"x":-278.27,"z":-144.91,"is_bot":false},{"t":674,"event":"Position","px":250,"py":675,"x":-255.73,"z":-158.75,"is_bot":false},{"t":679,"event":"Position","px":258,"py":679,"x":-247.82,"z":-163.17,"is_bot":false}]