[{"t":0,"event":"Position","px":686,"py":233,"x":233.17,"z":222.55,"is_bot":false},{"t":10,"event":"Position","px":674,"py":254,"x":222.24,"z":203.85,"is_bot":false},{"t":15,"event":"Position","px":638,"py":252,"x":190.9,"z":205.66,"is_bot":false},{"t":17,"event":"Loot","px":638,"py":252,"x":190.77,"z":205.54,"is_bot":false},{"t":21,"event":"Position","px":623,"py":274,"x":177.18,"z":186.55,"is_bot":false},{"t":26,"event":"Position","px":611,"py":311,"x":166.77,"z":153.53,"is_bot":false},{"t":31,"event":"Position","px":602,"py":323,"x":159.18,"z":142.94,"is_bot":false},{"t":36,"event":"Position","px":608,"py":334,"x":164.79,"z":133.83,"is_bot":false},{"t":41,"event":"Position","px":616,"py":371,"x":171.84,"z":100.7,"is_bot":false},{"t":46,"event":"Position","px":625,"py":389,"x":179.11,"z":85.46,"is_bot":false},{"t":47,"event":"Loot","px":625,"py":396,"x":179.27,"z":78.81,"is_bot":false},{"t":48,"event":"Loot","px":625,"py":400,"x":179.3,"z":75.78,"is_bot":false},{"t":51,"event":"Position","px":618,"py":394,"x":172.75,"z":80.55,"is_bot":false},{"t":53,"event":"Loot","px":612,"py":391,"x":168.29,"z":83.48,"is_bot":false},{"t":55,"event":"Loot","px":615,"py":397,"x":170.2,"z":78.37,"is_bot":false},{"t":56,"event":"Position","px":612,"py":396,"x":168.02,"z":78.61,"is_bot":false},{"t":61,"event":"BotKill","px":609,"py":399,"x":165.53,"z":76.06,"is_bot":false},{"t":66,"event":"Position","px":623,"py":407,"x":177.74,"z":68.96,"is_bot":false},{"t":71,"event":"Position","px":627,"py":399,"x":181.43,"z":76.0,"is_bot":false},{"t":76,"event":"Position","px":623,"py":414,"x":177.55,"z":63.14,"is_bot":false},{"t":81,"event":"Position","px":616,"py":418,"x":171.65,"z":59.25,"is_bot":false},{"t":84,"event":"Loot","px":613,"py":417,"x":168.35,"z":60.48,"is_bot":false},{"t":86,"event":"Position","px":611,"py":413,"x":166.59,"z":64.39,"is_bot":false},{"t":86,"event":"BotKill","px":610,"py":412,"x":166.41,"z":64.63,"is_bot":false},{"t":91,"event":"Position","px":626,"py":418,"x":180.18,"z":59.99,"is_bot":false},{"t":96,"event":"Position","px":614,"py":426,"x":170.01,"z":52.88,"is_bot":false},{"t":99,"event":"Loot","px":610,"py":426,"x":165.86,"z":52.98,"is_bot":false},{"t":101,"event":"Position","px":609,"py":434,"x":165.14,"z":45.16,"is_bot":false},{"t":106,"event":"Position","px":597,"py":419,"x":154.91,"z":59.12,"is_bot":false},{"t":106,"event":"Loot","px":597,"py":419,"x":154.91,"z":59.12,"is_bot":false},{"t":111,"event":"Position","px":588,"py":397,"x":146.99,"z":77.66,"is_bot":false},{"t":116,"event":"Position","px":583,"py":407,"x":142.26,"z":69.42,"is_bot":false},{"t":121,"event":"Position","px":584,"py":404,"x":143.49,"z":72.13,"is_bot":false},{"t":124,"event":"Loot","px":583,"py":398,"x":142.41,"z":77.17,"is_bot":false},{"t":124,"event":"Loot","px":583,"py":398,"x":142.41,"z":77.17,"is_bot":false},{"t":126,"event":"Position","px":577,"py":408,"x":136.82,"z":68.72,"is_bot":false},{"t":131,"event":"Position","px":566,"py":443,"x":127.33,"z":37.39,"is_bot":false},{"t":136,"event":"Position","px":543,"py":475,"x":107.61,"z":9.58,"is_bot":false},{"t":141,"event":"Position","px":539,"py":488,"x":104.1,"z":-1.67,"is_bot":false},{"t":146,"event":"Position","px":528,"py":491,"x":93.72,"z":-4.19,"is_bot":false},{"t":151,"event":"Position","px":519,"py":491,"x":85.94,"z":-4.72,"is_bot":false},{"t":156,"event":"Position","px":499,"py":460,"x":68.36,"z":22.68,"is_bot":false},{"t":161,"event":"Position","px":486,"py":437,"x":56.94,"z":42.64,"is_bot":false},{"t":166,"event":"Position","px":453,"py":460,"x":28.0,"z":22.36,"is_bot":false},{"t":171,"event":"Position","px":429,"py":477,"x":6.7,"z":8.15,"is_bot":false},{"t":176,"event":"BotKill","px":408,"py":480,"x":-11.2,"z":4.9,"is_bot":false},{"t":176,"event":"Position","px":409,"py":479,"x":-10.6,"z":5.69,"is_bot":false},{"t":178,"event":"Loot","px":407,"py":478,"x":-12.23,"z":7.09,"is_bot":false},{"t":181,"event":"Position","px":421,"py":433,"x":0.22,"z":46.39,"is_bot":false},{"t":186,"event":"Position","px":424,"py":401,"x":2.26,"z":74.99,"is_bot":false},{"t":191,"event":"Position","px":417,"py":402,"x":-3.35,"z":73.86,"is_bot":false},{"t":194,"event":"BotKill","px":416,"py":399,"x":-4.04,"z":76.01,"is_bot":false},{"t":197,"event":"Position","px":414,"py":394,"x":-6.16,"z":80.9,"is_bot":false},{"t":199,"event":"Loot","px":407,"py":386,"x":-12.01,"z":87.4,"is_bot":false},{"t":199,"event":"Loot","px":407,"py":386,"x":-12.01,"z":87.4,"is_bot":false},{"t":200,"event":"Loot","px":407,"py":386,"x":-12.01,"z":87.4,"is_bot":false},{"t":200,"event":"Loot","px":407,"py":386,"x":-12.01,"z":87.4,"is_bot":false},{"t":201,"event":"Loot","px":407,"py":386,"x":-12.01,"z":87.4,"is_bot":false},{"t":202,"event":"Position","px":408,"py":386,"x":-11.77,"z":87.66,"is_bot":false},{"t":207,"event":"Position","px":390,"py":391,"x":-27.58,"z":83.45,"is_bot":false},{"t":208,"event":"Loot","px":390,"py":391,"x":-27.58,"z":83.45,"is_bot":false},{"t":211,"event":"Loot","px":395,"py":379,"x":-22.88,"z":93.75,"is_bot":false},{"t":212,"event":"Position","px":395,"py":379,"x":-22.88,"z":93.75,"is_bot":false},{"t":217,"event":"Position","px":376,"py":397,"x":-39.38,"z":77.72,"is_bot":false},{"t":221,"event":"Loot","px":354,"py":415,"x":-58.87,"z":61.91,"is_bot":false},{"t":222,"event":"Position","px":352,"py":412,"x":-60.27,"z":65.01,"is_bot":false},{"t":225,"event":"Loot","px":353,"py":391,"x":-60.1,"z":82.95,"is_bot":false},{"t":227,"event":"Position","px":354,"py":392,"x":-58.88,"z":82.84,"is_bot":false},{"t":227,"event":"Loot","px":354,"py":392,"x":-58.88,"z":82.84,"is_bot":false},{"t":231,"event":"Loot","px":352,"py":387,"x":-60.52,"z":87.04,"is_bot":false},{"t":232,"event":"Position","px":349,"py":388,"x":-63.58,"z":86.0,"is_bot":false},{"t":237,"event":"Position","px":342,"py":415,"x":-69.59,"z":62.48,"is_bot":false},{"t":242,"event":"Position","px":346,"py":446,"x":-65.61,"z":35.3,"is_bot":false},{"t":246,"event":"Loot","px":335,"py":449,"x":-75.4,"z":31.95,"is_bot":false},{"t":247,"event":"Position","px":332,"py":453,"x":-78.04,"z":28.7,"is_bot":false},{"t":252,"event":"Position","px":309,"py":463,"x":-98.86,"z":19.86,"is_bot":false},{"t":252,"event":"Loot","px":309,"py":463,"x":-98.86,"z":19.86,"is_bot":false},{"t":257,"event":"Position","px":287,"py":485,"x":-117.43,"z":0.44,"is_bot":false},{"t":261,"event":"BotKill","px":284,"py":492,"x":-120.5,"z":-5.22,"is_bot":false},{"t":262,"event":"Position","px":283,"py":495,"x":-121.07,"z":-7.84,"is_bot":false},{"t":266,"event":"Loot","px":275,"py":510,"x":-128.72,"z":-21.36,"is_bot":false},{"t":267,"event":"Position","px":277,"py":518,"x":-126.56,"z":-27.84,"is_bot":false},{"t":268,"event":"Loot","px":278,"py":524,"x":-126.04,"z":-33.18,"is_bot":false},{"t":268,"event":"Loot","px":278,"py":524,"x":-126.04,"z":-33.18,"is_bot":false},{"t":272,"event":"Position","px":296,"py":531,"x":-109.89,"z":-39.55,"is_bot":false},{"t":275,"event":"Loot","px":308,"py":531,"x":-99.21,"z":-39.74,"is_bot":false},{"t":277,"event":"Position","px":307,"py":528,"x":-100.58,"z":-36.63,"is_bot":false},{"t":279,"event":"Loot","px":307,"py":528,"x":-100.58,"z":-36.63,"is_bot":false},{"t":282,"event":"Position","px":306,"py":534,"x":-100.71,"z":-42.5,"is_bot":false},{"t":283,"event":"Loot","px":306,"py":534,"x":-100.71,"z":-42.5,"is_bot":false},{"t":285,"event":"Loot","px":306,"py":539,"x":-101.24,"z":-46.48,"is_bot":false},{"t":287,"event":"Position","px":312,"py":539,"x":-95.75,"z":-47.11,"is_bot":false},{"t":292,"event":"Position","px":346,"py":550,"x":-65.86,"z":-56.22,"is_bot":false},{"t":294,"event":"BotKill","px":350,"py":552,"x":-62.8,"z":-58.01,"is_bot":false},{"t":295,"event":"Loot","px":351,"py":552,"x":-61.48,"z":-58.45,"is_bot":false},{"t":297,"event":"Position","px":350,"py":547,"x":-61.96,"z":-53.39,"is_bot":false},{"t":301,"event":"BotKill","px":341,"py":540,"x":-70.7,"z":-48.0,"is_bot":false},{"t":302,"event":"Position","px":340,"py":538,"x":-71.01,"z":-46.24,"is_bot":false},{"t":307,"event":"Position","px":345,"py":542,"x":-66.36,"z":-49.15,"is_bot":false},{"t":311,"event":"BotKill","px":340,"py":536,"x":-70.78,"z":-44.02,"is_bot":false},{"t":312,"event":"Position","px":340,"py":537,"x":-71.04,"z":-45.09,"is_bot":false},{"t":313,"event":"BotKill","px":340,"py":538,"x":-70.91,"z":-45.55,"is_bot":false},{"t":317,"event":"BotKill","px":341,"py":533,"x":-70.73,"z":-41.07,"is_bot":false},{"t":317,"event":"Position","px":340,"py":534,"x":-70.79,"z":-42.32,"is_bot":false},{"t":320,"event":"Loot","px":343,"py":543,"x":-68.66,"z":-49.96,"is_bot":false},{"t":321,"event":"Loot","px":344,"py":546,"x":-67.43,"z":-52.6,"is_bot":false},{"t":322,"event":"Position","px":347,"py":549,"x":-65.36,"z":-55.63,"is_bot":false},{"t":323,"event":"Loot","px":350,"py":553,"x":-62.44,"z":-59.04,"is_bot":false},{"t":325,"event":"Loot","px":351,"py":552,"x":-61.44,"z":-58.24,"is_bot":false},{"t":325,"event":"Loot","px":351,"py":552,"x":-61.44,"z":-58.24,"is_bot":false},{"t":327,"event":"Loot","px":360,"py":556,"x":-53.89,"z":-61.93,"is_bot":false},{"t":327,"event":"Position","px":360,"py":556,"x":-53.89,"z":-61.93,"is_bot":false},{"t":332,"event":"Position","px":352,"py":567,"x":-60.53,"z":-71.46,"is_bot":false},{"t":342,"event":"Position","px":341,"py":568,"x":-69.95,"z":-72.22,"is_bot":false},{"t":342,"event":"Loot","px":341,"py":568,"x":-69.95,"z":-72.22,"is_bot":false},{"t":346,"event":"Loot","px":332,"py":561,"x":-78.13,"z":-66.05,"is_bot":false},{"t":347,"event":"Position","px":332,"py":558,"x":-77.81,"z":-63.35,"is_bot":false},{"t":352,"event":"Position","px":339,"py":557,"x":-71.88,"z":-62.93,"is_bot":false},{"t":357,"event":"Position","px":347,"py":562,"x":-65.44,"z":-67.1,"is_bot":false},{"t":362,"event":"Position","px":351,"py":567,"x":-61.67,"z":-71.19,"is_bot":false},{"t":367,"event":"Position","px":384,"py":574,"x":-32.15,"z":-77.63,"is_bot":false},{"t":369,"event":"Loot","px":387,"py":574,"x":-30.28,"z":-77.43,"is_bot":false},{"t":373,"event":"Position","px":380,"py":565,"x":-36.09,"z":-69.74,"is_bot":false},{"t":374,"event":"Loot","px":380,"py":565,"x":-36.28,"z":-69.56,"is_bot":false},{"t":378,"event":"Position","px":385,"py":550,"x":-31.82,"z":-56.38,"is_bot":false},{"t":383,"event":"Position","px":389,"py":534,"x":-27.86,"z":-42.63,"is_bot":false},{"t":385,"event":"Loot","px":389,"py":533,"x":-28.0,"z":-41.5,"is_bot":false},{"t":388,"event":"Position","px":389,"py":520,"x":-28.34,"z":-30.03,"is_bot":false},{"t":393,"event":"Position","px":388,"py":505,"x":-28.98,"z":-16.92,"is_bot":false},{"t":394,"event":"Loot","px":388,"py":505,"x":-29.27,"z":-16.43,"is_bot":false},{"t":398,"event":"Position","px":398,"py":498,"x":-20.1,"z":-10.31,"is_bot":false},{"t":403,"event":"Position","px":427,"py":495,"x":5.03,"z":-7.89,"is_bot":false},{"t":408,"event":"Position","px":438,"py":493,"x":14.71,"z":-6.74,"is_bot":false},{"t":413,"event":"Position","px":460,"py":489,"x":33.91,"z":-2.76,"is_bot":false},{"t":418,"event":"Position","px":456,"py":503,"x":31.19,"z":-14.85,"is_bot":false},{"t":423,"event":"Position","px":463,"py":506,"x":36.97,"z":-17.45,"is_bot":false},{"t":427,"event":"Loot","px":467,"py":496,"x":40.09,"z":-8.66,"is_bot":false},{"t":433,"event":"Position","px":457,"py":511,"x":31.57,"z":-22.46,"is_bot":false},{"t":435,"event":"Loot","px":457,"py":511,"x":31.57,"z":-22.46,"is_bot":false},{"t":438,"event":"Position","px":451,"py":526,"x":26.45,"z":-34.97,"is_bot":false},{"t":439,"event":"Loot","px":451,"py":526,"x":26.45,"z":-34.97,"is_bot":false},{"t":443,"event":"Position","px":446,"py":527,"x":22.31,"z":-36.4,"is_bot":false},{"t":448,"event":"Position","px":454,"py":549,"x":29.22,"z":-55.83,"is_bot":false},{"t":453,"event":"Position","px":458,"py":586,"x":32.33,"z":-88.28,"is_bot":false},{"t":458,"event":"Position","px":449,"py":622,"x":24.21,"z":-119.39,"is_bot":false},{"t":463,"event":"Position","px":439,"py":637,"x":16.22,"z":-132.59,"is_bot":false},{"t":468,"event":"Position","px":419,"py":640,"x":-1.48,"z":-135.88,"is_bot":false},{"t":473,"event":"Position","px":415,"py":613,"x":-5.14,"z":-111.76,"is_bot":false},{"t":475,"event":"Loot","px":415,"py":613,"x":-5.14,"z":-111.76,"is_bot":false},{"t":478,"event":"Position","px":422,"py":595,"x":0.46,"z":-95.77,"is_bot":false},{"t":483,"event":"Position","px":401,"py":581,"x":-17.89,"z":-83.75,"is_bot":false},{"t":488,"event":"Position","px":371,"py":594,"x":-43.58,"z":-95.39,"is_bot":false},{"t":493,"event":"Position","px":352,"py":628,"x":-60.66,"z":-125.14,"is_bot":false},{"t":498,"event":"Position","px":337,"py":667,"x":-73.68,"z":-159.01,"is_bot":false},{"t":501,"event":"Loot","px":336,"py":664,"x":-75.06,"z":-156.56,"is_bot":false},{"t":503,"event":"Loot","px":320,"py":658,"x":-88.39,"z":-150.96,"is_bot":false},{"t":503,"event":"Position","px":321,"py":658,"x":-88.31,"z":-151.0,"is_bot":false},{"t":508,"event":"Position","px":325,"py":691,"x":-84.4,"z":-179.91,"is_bot":false},{"t":513,"event":"Position","px":292,"py":692,"x":-112.98,"z":-181.32,"is_bot":false},{"t":518,"event":"Position","px":258,"py":695,"x":-143.34,"z":-183.53,"is_bot":false},{"t":520,"event":"Loot","px":255,"py":693,"x":-145.79,"z":-181.76,"is_bot":false},{"t":523,"event":"Position","px":255,"py":678,"x":-145.86,"z":-168.64,"is_bot":false},{"t":528,"event":"Position","px":235,"py":661,"x":-163.24,"z":-154.3,"is_bot":false},{"t":531,"event":"Loot","px":234,"py":658,"x":-164.63,"z":-151.48,"is_bot":false},{"t":533,"event":"Position","px":232,"py":636,"x":-166.32,"z":-132.29,"is_bot":false},{"t":538,"event":"Position","px":231,"py":595,"x":-166.84,"z":-96.19,"is_bot":false},{"t":543,"event":"Position","px":266,"py":577,"x":-135.98,"z":-80.15,"is_bot":false},{"t":548,"event":"Position","px":298,"py":577,"x":-107.79,"z":-80.04,"is_bot":false},{"t":554,"event":"Position","px":310,"py":549,"x":-97.38,"z":-55.28,"is_bot":false},{"t":559,"event":"Position","px":321,"py":513,"x":-88.25,"z":-24.26,"is_bot":false},{"t":564,"event":"Position","px":299,"py":495,"x":-106.9,"z":-7.95,"is_bot":false},{"t":567,"event":"Loot","px":288,"py":487,"x":-116.68,"z":-1.15,"is_bot":false},{"t":569,"event":"Position","px":285,"py":489,"x":-119.19,"z":-2.38,"is_bot":false},{"t":574,"event":"Position","px":267,"py":487,"x":-135.11,"z":-1.09,"is_bot":false},{"t":579,"event":"Position","px":242,"py":484,"x":-157.05,"z":1.52,"is_bot":false},{"t":584,"event":"Position","px":224,"py":493,"x":-173.21,"z":-6.23,"is_bot":false},{"t":585,"event":"Loot","px":224,"py":493,"x":-173.21,"z":-6.23,"is_bot":false},{"t":589,"event":"Position","px":245,"py":494,"x":-154.34,"z":-6.77,"is_bot":false},{"t":594,"event":"Position","px":257,"py":506,"x":-143.81,"z":-17.84,"is_bot":false},{"t":599,"event":"Position","px":269,"py":517,"x":-133.97,"z":-27.51,"is_bot":false},{"t":604,"event":"Position","px":272,"py":536,"x":-131.17,"z":-44.07,"is_bot":false},{"t":614,"event":"Position","px":263,"py":549,"x":-138.45,"z":-55.94,"is_bot":false},{"t":624,"event":"Position","px":250,"py":555,"x":-150.46,"z":-60.88,"is_bot":false},{"t":629,"event":"Position","px":260,"py":555,"x":-141.49,"z":-60.47,"is_bot":false},{"t":634,"event":"Position","px":270,"py":540,"x":-132.81,"z":-47.36,"is_bot":false},{"t":639,"event":"Position","px":273,"py":539,"x":-129.95,"z":-46.55,"is_bot":false},{"t":644,"event":"Position","px":267,"py":519,"x":-135.18,"z":-29.47,"is_bot":false},{"t":647,"event":"Loot","px":263,"py":515,"x":-138.53,"z":-25.63,"is_bot":false},{"t":649,"event":"Position","px":254,"py":510,"x":-147.19,"z":-21.33,"is_bot":false},{"t":654,"event":"Position","px":223,"py":519,"x":-174.13,"z":-28.71,"is_bot":false},{"t":659,"event":"Position","px":222,"py":542,"x":-175.06,"z":-49.59,"is_bot":false},{"t":664,"event":"Position","px":227,"py":544,"x":-170.11,"z":-51.2,"is_bot":false},{"t":669,"event":"Position","px":254,"py":558,"x":-147.12,"z":-63.85,"is_bot":false},{"t":674,"event":"Position","px":257,"py":539,"x":-143.88,"z":-46.66,"is_bot":false},{"t":679,"event":"Position","px":248,"py":523,"x":-152.04,"z":-32.89,"is_bot":false},{"t":684,"event":"Position","px":252,"py":557,"x":-148.26,"z":-62.22,"is_bot":false},{"t":689,"event":"Position","px":279,"py":569,"x":-124.97,"z":-72.74,"is_bot":false},{"t":694,"event":"Position","px":306,"py":587,"x":-101.1,"z":-88.93,"is_bot":false},{"t":699,"event":"Position","px":339,"py":595,"x":-71.68,"z":-96.33,"is_bot":false},{"t":704,"event":"Position","px":374,"py":588,"x":-41.23,"z":-89.59,"is_bot":false},{"t":709,"event":"Position","px":410,"py":584,"x":-9.94,"z":-86.7,"is_bot":false},{"t":714,"event":"Position","px":424,"py":597,"x":2.74,"z":-97.43,"is_bot":false},{"t":717,"event":"Loot","px":422,"py":598,"x":1.23,"z":-98.33,"is_bot":false},{"t":719,"event":"Position","px":441,"py":601,"x":17.96,"z":-101.29,"is_bot":false},{"t":724,"event":"Position","px":471,"py":606,"x":43.91,"z":-105.48,"is_bot":false},{"t":725,"event":"Loot","px":471,"py":606,"x":43.91,"z":-105.48,"is_bot":false},{"t":730,"event":"Position","px":494,"py":612,"x":64.18,"z":-110.64,"is_bot":false},{"t":735,"event":"Position","px":515,"py":626,"x":82.66,"z":-123.38,"is_bot":false},{"t":740,"event":"Position","px":524,"py":638,"x":90.11,"z":-133.46,"is_bot":false},{"t":745,"event":"Position","px":543,"py":642,"x":107.21,"z":-137.37,"is_bot":false},{"t":750,"event":"Position","px":564,"py":658,"x":125.93,"z":-151.36,"is_bot":false},{"t":755,"event":"Position","px":587,"py":665,"x":146.13,"z":-157.67,"is_bot":false},{"t":760,"event":"Position","px":606,"py":647,"x":162.54,"z":-141.39,"is_bot":false},{"t":765,"event":"Position","px":620,"py":613,"x":175.26,"z":-111.8,"is_bot":false},{"t":770,"event":"Position","px":633,"py":579,"x":186.61,"z":-82.13,"is_bot":false},{"t":775,"event":"Position","px":639,"py":583,"x":191.26,"z":-85.51,"is_bot":false},{"t":775,"event":"Loot","px":639,"py":583,"x":191.26,"z":-85.51,"is_bot":false},{"t":780,"event":"Position","px":646,"py":567,"x":197.76,"z":-71.34,"is_bot":false}]